{
  "ComponentIndexes": {},
  "ControlUniqueGuids": {},
  "ControlUniqueIds": {
    "App": 1,
    "Button1": 173,
    "Button3": 118,
    "ConfirmationScreen": 94,
    "DataCardKey1_1": 154,
    "DataCardKey1_2": 50,
    "DataCardKey10_1": 131,
    "DataCardKey10_2": 27,
    "DataCardKey11_1": 136,
    "DataCardKey11_2": 32,
    "DataCardKey12_1": 141,
    "DataCardKey12_2": 37,
    "DataCardKey14_1": 146,
    "DataCardKey14_2": 42,
    "DataCardKey15_1": 150,
    "DataCardKey15_2": 46,
    "DataCardKey2_1": 159,
    "DataCardKey2_2": 55,
    "DataCardKey3_1": 164,
    "DataCardKey3_2": 60,
    "DataCardKey4": 179,
    "DataCardKey5_1": 169,
    "DataCardKey5_2": 65,
    "DataCardKey6": 185,
    "DataCardKey7": 190,
    "DataCardKey8": 195,
    "DataCardKey9_1": 126,
    "DataCardKey9_2": 22,
    "DataCardValue1_1": 155,
    "DataCardValue1_2": 51,
    "DataCardValue10_1": 132,
    "DataCardValue10_2": 28,
    "DataCardValue11_1": 137,
    "DataCardValue11_2": 33,
    "DataCardValue12_1": 142,
    "DataCardValue12_2": 38,
    "DataCardValue14_1": 147,
    "DataCardValue14_2": 43,
    "DataCardValue15_1": 151,
    "DataCardValue15_2": 47,
    "DataCardValue2_1": 160,
    "DataCardValue2_2": 56,
    "DataCardValue3_1": 165,
    "DataCardValue3_2": 61,
    "DataCardValue4": 180,
    "DataCardValue5_1": 170,
    "DataCardValue5_2": 66,
    "DataCardValue6": 186,
    "DataCardValue7": 191,
    "DataCardValue8": 196,
    "DataCardValue9_1": 127,
    "DataCardValue9_2": 23,
    "Department_DataCard1": 175,
    "Department_DataCard2_1": 124,
    "Department_DataCard2_2": 20,
    "End_Date_DataCard1_1": 157,
    "End_Date_DataCard1_2": 53,
    "ErrorMessage1_1": 156,
    "ErrorMessage1_2": 52,
    "ErrorMessage10_1": 133,
    "ErrorMessage10_2": 29,
    "ErrorMessage11_1": 138,
    "ErrorMessage11_2": 34,
    "ErrorMessage12_1": 143,
    "ErrorMessage12_2": 39,
    "ErrorMessage13_1": 148,
    "ErrorMessage13_2": 44,
    "ErrorMessage2_1": 161,
    "ErrorMessage2_2": 57,
    "ErrorMessage3_1": 166,
    "ErrorMessage3_2": 62,
    "ErrorMessage4": 181,
    "ErrorMessage5_1": 171,
    "ErrorMessage5_2": 67,
    "ErrorMessage6": 187,
    "ErrorMessage7": 192,
    "ErrorMessage8": 197,
    "ErrorMessage9_1": 128,
    "ErrorMessage9_2": 24,
    "Form1_1": 123,
    "Form1_2": 19,
    "homePage": 99,
    "Host": 3,
    "Icon1": 86,
    "Image1": 77,
    "Image1_1": 69,
    "Image2": 100,
    "Image2_1": 5,
    "Image3": 95,
    "Image3_1": 200,
    "Image3_2": 119,
    "Image4": 96,
    "Image4_1": 201,
    "Image4_2": 120,
    "Image5": 102,
    "Image5_1": 109,
    "Image5_2": 104,
    "Image5_3": 110,
    "Image5_4": 9,
    "Image5_5": 15,
    "Image5_6": 14,
    "Image5_7": 7,
    "Label1": 81,
    "Label1_1": 84,
    "Label1_2": 72,
    "Label1_3": 74,
    "Label2": 79,
    "Label2_1": 70,
    "Label3": 97,
    "Label3_1": 202,
    "Label4": 98,
    "Label4_1": 203,
    "Label4_2": 121,
    "Label5": 112,
    "Label5_1": 111,
    "Label5_2": 106,
    "Label5_3": 105,
    "Label5_4": 16,
    "Label5_5": 11,
    "Label5_6": 10,
    "Label5_7": 17,
    "Label6": 78,
    "Label8": 87,
    "NoVendorFound": 116,
    "PR": 122,
    "purchaseOrderForm": 174,
    "purchaseRequstion": 172,
    "Rectangle1": 101,
    "Rectangle1_1": 107,
    "Rectangle1_2": 103,
    "Rectangle1_3": 108,
    "Rectangle1_4": 6,
    "Rectangle1_5": 12,
    "Rectangle1_6": 8,
    "Rectangle1_7": 13,
    "Rectangle2": 83,
    "Reg Cost Disb_DataCard1": 177,
    "Region_DataCard1": 176,
    "Region_DataCard2_1": 129,
    "Region_DataCard2_2": 25,
    "Replicate_ConfirmationScreen": 199,
    "Replicate_HomeSCreen": 4,
    "Replicate_PR": 18,
    "Replicate_SplashScreen": 68,
    "Replicate_Vendor": 71,
    "Service and Bussiness Case_DataCard1": 189,
    "Service and Bussiness Case_DataCard3_1": 144,
    "Service and Bussiness Case_DataCard3_2": 40,
    "Service_Provider_Known_DataCard1_1": 162,
    "Service_Provider_Known_DataCard1_2": 58,
    "splashScreen": 76,
    "Start_Date_DataCard1_1": 152,
    "Start_Date_DataCard1_2": 48,
    "StarVisible1_1": 153,
    "StarVisible1_2": 49,
    "StarVisible10_1": 130,
    "StarVisible10_2": 26,
    "StarVisible11_1": 135,
    "StarVisible11_2": 31,
    "StarVisible12_1": 140,
    "StarVisible12_2": 36,
    "StarVisible13_1": 145,
    "StarVisible13_2": 41,
    "StarVisible2_1": 158,
    "StarVisible2_2": 54,
    "StarVisible3_1": 163,
    "StarVisible3_2": 59,
    "StarVisible4": 182,
    "StarVisible5_1": 168,
    "StarVisible5_2": 64,
    "StarVisible6": 188,
    "StarVisible7": 193,
    "StarVisible8": 198,
    "StarVisible9_1": 125,
    "StarVisible9_2": 21,
    "Summary_DataCard1": 184,
    "Summary_DataCard2_1": 139,
    "Summary_DataCard2_2": 35,
    "TextInput1": 82,
    "TextInput1_1": 85,
    "TextInput1_2": 73,
    "TextInput1_3": 75,
    "TextInput2": 88,
    "TextInput2_1": 89,
    "TextInput2_2": 90,
    "TextInput2_3": 91,
    "TextInput2_4": 92,
    "TextInput2_5": 93,
    "Unit Cost Disb_DataCard1": 183,
    "UnitEntity_DataCard1": 178,
    "UnitEntity_DataCard2_1": 134,
    "UnitEntity_DataCard2_2": 30,
    "Units Needed_DataCard1": 194,
    "Units Needed_DataCard2_1": 149,
    "Units Needed_DataCard2_2": 45,
    "Vendor": 80,
    "Vendor_DataCard2_1": 167,
    "Vendor_DataCard2_2": 63
  },
  "FunctionParamsInvariantScripts": {},
  "FunctionParamsInvariantScriptsOnInstances": {},
  "HeaderLastSavedDateTimeUTC": "08/03/2023 10:23:43",
  "IsLegacyComponentAllowGlobalScopeCase": false,
  "LocalConnectionIDReferences": {
    "4320845a-f039-4291-8e4c-6e4835b22bed": "\"/providers/microsoft.powerapps/apis/shared_sharepointonline/connections/20118889000f4adcbe3763f03c8e918f\"",
    "c0fb478d-c635-43f7-ba3e-a1629d3b4519": "\"/providers/microsoft.powerapps/apis/shared_sharepointonline/connections/20118889000f4adcbe3763f03c8e918f\""
  },
  "LocalDatabaseReferencesAsEmpty": false,
  "LocalResourceFileNames": {
    "Confirmed-cuate": "0001.png",
    "icons8-business-report-100": "0002.png",
    "icons8-login-64": "0003.png",
    "icons8-order-100": "0004.png",
    "icons8-purchase-order-50": "0005.png",
    "icons8-purchase-order-50_1": "0006.png",
    "icons8-user-100": "0007.png",
    "icons8-user-64": "0008.png",
    "icons8-vendor-100": "0009.png",
    "image": "0010.jpg",
    "image_1": "0011.jpg",
    "Questions-pana-removebg-preview": "0012.png",
    "Questions-pana-removebg-preview_1": "0013.png",
    "XEBIA2": "0014.jpg",
    "XebiaBg": "0015.jpeg"
  },
  "LocalResourceRootPaths": {
    "Confirmed-cuate": "https://docserverpwaprodneu.blob.core.windows.net/8e084fc4-227a-4fd6-a01d-749d2ea5c709-1/resource/Assets0Images00001.png?sv=2018-03-28&sr=b&sig=jgxv6tD7y8dwpxb%2FHkFH8N8pCMC56wK3eTzp%2FrYBdkg%3D&spr=https&se=2023-08-04T10%3A36%3A19Z&sp=r",
    "icons8-business-report-100": "https://docserverpwaprodneu.blob.core.windows.net/8e084fc4-227a-4fd6-a01d-749d2ea5c709-1/resource/Assets0Images00002.png?sv=2018-03-28&sr=b&sig=vmwY3mHIp0KMt9YAitseVW9vgjLRWbSu5iPGl6YakAY%3D&spr=https&se=2023-08-04T10%3A36%3A19Z&sp=r",
    "icons8-login-64": "https://docserverpwaprodneu.blob.core.windows.net/8e084fc4-227a-4fd6-a01d-749d2ea5c709-1/resource/Assets0Images00003.png?sv=2018-03-28&sr=b&sig=ksCErxu6MOUcSDUSBkG9BYYWBxa629bsSA1TTXjE29s%3D&spr=https&se=2023-08-04T10%3A36%3A19Z&sp=r",
    "icons8-order-100": "https://docserverpwaprodneu.blob.core.windows.net/8e084fc4-227a-4fd6-a01d-749d2ea5c709-1/resource/Assets0Images00004.png?sv=2018-03-28&sr=b&sig=lxCJjtZLtKoIlt6F4D7lhG8GKezC%2BZA5cpIbTx19KOc%3D&spr=https&se=2023-08-04T10%3A36%3A19Z&sp=r",
    "icons8-purchase-order-50": "https://docserverpwaprodneu.blob.core.windows.net/8e084fc4-227a-4fd6-a01d-749d2ea5c709-1/resource/Assets0Images00005.png?sv=2018-03-28&sr=b&sig=uOzkeAaXxgAs25t%2FN2Lqe4SCdK3qMk3NFtqHdM%2BCUOk%3D&spr=https&se=2023-08-04T10%3A36%3A19Z&sp=r",
    "icons8-purchase-order-50_1": "https://docserverpwaprodneu.blob.core.windows.net/8e084fc4-227a-4fd6-a01d-749d2ea5c709-1/resource/Assets0Images00006.png?sv=2018-03-28&sr=b&sig=Q0z5EPrE5URfjKPq4xNC6tofgIGYRSdxvCnJ1Mqbmnw%3D&spr=https&se=2023-08-04T10%3A36%3A19Z&sp=r",
    "icons8-user-100": "https://docserverpwaprodneu.blob.core.windows.net/8e084fc4-227a-4fd6-a01d-749d2ea5c709-1/resource/Assets0Images00007.png?sv=2018-03-28&sr=b&sig=n3QvHEv7unk5wLEuMlpSHJ8W9cJW%2Fc8UxFeegO0s1bQ%3D&spr=https&se=2023-08-04T10%3A36%3A19Z&sp=r",
    "icons8-user-64": "https://docserverpwaprodneu.blob.core.windows.net/8e084fc4-227a-4fd6-a01d-749d2ea5c709-1/resource/Assets0Images00008.png?sv=2018-03-28&sr=b&sig=%2BvM%2Fkj7gkwSoQ2egOUWCD0Hphzevybq8CWeonz4WPEc%3D&spr=https&se=2023-08-04T10%3A36%3A19Z&sp=r",
    "icons8-vendor-100": "https://docserverpwaprodneu.blob.core.windows.net/8e084fc4-227a-4fd6-a01d-749d2ea5c709-1/resource/Assets0Images00009.png?sv=2018-03-28&sr=b&sig=JyKSwS8%2B%2FsQWT0ictisf9%2BmlSx05GJtknOxQAHgCv%2FE%3D&spr=https&se=2023-08-04T10%3A36%3A19Z&sp=r",
    "image": "https://docserverpwaprodneu.blob.core.windows.net/8e084fc4-227a-4fd6-a01d-749d2ea5c709-1/resource/Assets0Images00010.jpg?sv=2018-03-28&sr=b&sig=jyLPEll36u%2F%2BYI2MnJFm0H7ZVG2NKuSFfYxc3njswTs%3D&spr=https&se=2023-08-04T10%3A36%3A19Z&sp=r",
    "image_1": "https://docserverpwaprodneu.blob.core.windows.net/8e084fc4-227a-4fd6-a01d-749d2ea5c709-1/resource/Assets0Images00011.jpg?sv=2018-03-28&sr=b&sig=O2VUR7rq3fRSetGUi84p5PtTPp4ukk16CrVy7ezw7O4%3D&spr=https&se=2023-08-04T10%3A36%3A19Z&sp=r",
    "Questions-pana-removebg-preview": "https://docserverpwaprodneu.blob.core.windows.net/8e084fc4-227a-4fd6-a01d-749d2ea5c709-1/resource/Assets0Images00012.png?sv=2018-03-28&sr=b&sig=9zhTKGN9VP1wgWIsIJ11xm25j0M%2FPwkQJDb5BViJqcE%3D&spr=https&se=2023-08-04T10%3A36%3A19Z&sp=r",
    "Questions-pana-removebg-preview_1": "https://docserverpwaprodneu.blob.core.windows.net/8e084fc4-227a-4fd6-a01d-749d2ea5c709-1/resource/Assets0Images00013.png?sv=2018-03-28&sr=b&sig=2Ut4GRU8kJ1tkxJTik8u5ZXeuJTzXU8Bp7ck0eDU%2FdU%3D&spr=https&se=2023-08-04T10%3A36%3A19Z&sp=r",
    "XEBIA2": "https://docserverpwaprodneu.blob.core.windows.net/8e084fc4-227a-4fd6-a01d-749d2ea5c709-1/resource/Assets0Images00014.jpg?sv=2018-03-28&sr=b&sig=CkQyUlt2qvu%2FulXiNxONkCcyrBD5FqbUTM16cQvizyA%3D&spr=https&se=2023-08-04T10%3A36%3A19Z&sp=r",
    "XebiaBg": "https://docserverpwaprodneu.blob.core.windows.net/8e084fc4-227a-4fd6-a01d-749d2ea5c709-1/resource/Assets0Images00015.jpeg?sv=2018-03-28&sr=b&sig=SRJa%2B6rSwBoo8Z4kyELf0i%2BK7asrPHyeDngmADXYAH8%3D&spr=https&se=2023-08-04T10%3A36%3A19Z&sp=r"
  },
  "OrderComponentMetadata": {},
  "OrderComponentTemplate": {},
  "OrderDataSource": {
    "ComboBoxSample": 0,
    "CustomGallerySample": 1,
    "dep-dB1": 2,
    "Dep-db1": 3,
    "Dep-db1_1": 4,
    "Dep-db1_2": 5,
    "Dep-db1_3": 6,
    "Dep-db1_4": 7,
    "Dep-db1_5": 8,
    "Dep-db1_6": 9,
    "Dep-db1_7": 10,
    "DropDownSample": 11,
    "Ent-dB1": 12,
    "PO": 13,
    "Reg-db1": 14,
    "Reg-db1_1": 15,
    "Reg-db1_2": 16,
    "Reg-db1_3": 17,
    "Reg-db1_4": 18
  },
  "OrderGroupControls": {},
  "OrderPcfTemplate": {},
  "OrderTemplate": {},
  "OrderXMLTemplate": {
    "button": 10,
    "datepicker": 7,
    "dropdown": 4,
    "form": 3,
    "icon": 9,
    "image": 0,
    "label": 2,
    "rectangle": 1,
    "richTextEditor": 6,
    "text": 5,
    "toggleSwitch": 8
  },
  "OverridablePropertiesEntry": {
    "App": {},
    "Button1": {},
    "Button3": {},
    "ConfirmationScreen": {},
    "DataCardKey1_1": {},
    "DataCardKey1_2": {},
    "DataCardKey10_1": {},
    "DataCardKey10_2": {},
    "DataCardKey11_1": {},
    "DataCardKey11_2": {},
    "DataCardKey12_1": {},
    "DataCardKey12_2": {},
    "DataCardKey14_1": {},
    "DataCardKey14_2": {},
    "DataCardKey15_1": {},
    "DataCardKey15_2": {},
    "DataCardKey2_1": {},
    "DataCardKey2_2": {},
    "DataCardKey3_1": {},
    "DataCardKey3_2": {},
    "DataCardKey4": {},
    "DataCardKey5_1": {},
    "DataCardKey5_2": {},
    "DataCardKey6": {},
    "DataCardKey7": {},
    "DataCardKey8": {},
    "DataCardKey9_1": {},
    "DataCardKey9_2": {},
    "DataCardValue1_1": {},
    "DataCardValue1_2": {},
    "DataCardValue10_1": {},
    "DataCardValue10_2": {},
    "DataCardValue11_1": {},
    "DataCardValue11_2": {},
    "DataCardValue12_1": {},
    "DataCardValue12_2": {},
    "DataCardValue14_1": {},
    "DataCardValue14_2": {},
    "DataCardValue15_1": {},
    "DataCardValue15_2": {},
    "DataCardValue2_1": {},
    "DataCardValue2_2": {},
    "DataCardValue3_1": {},
    "DataCardValue3_2": {},
    "DataCardValue4": {},
    "DataCardValue5_1": {},
    "DataCardValue5_2": {},
    "DataCardValue6": {},
    "DataCardValue7": {},
    "DataCardValue8": {},
    "DataCardValue9_1": {},
    "DataCardValue9_2": {},
    "Department_DataCard1": {},
    "Department_DataCard2_1": {},
    "Department_DataCard2_2": {},
    "End_Date_DataCard1_1": {},
    "End_Date_DataCard1_2": {},
    "ErrorMessage1_1": {},
    "ErrorMessage1_2": {},
    "ErrorMessage10_1": {},
    "ErrorMessage10_2": {},
    "ErrorMessage11_1": {},
    "ErrorMessage11_2": {},
    "ErrorMessage12_1": {},
    "ErrorMessage12_2": {},
    "ErrorMessage13_1": {},
    "ErrorMessage13_2": {},
    "ErrorMessage2_1": {},
    "ErrorMessage2_2": {},
    "ErrorMessage3_1": {},
    "ErrorMessage3_2": {},
    "ErrorMessage4": {},
    "ErrorMessage5_1": {},
    "ErrorMessage5_2": {},
    "ErrorMessage6": {},
    "ErrorMessage7": {},
    "ErrorMessage8": {},
    "ErrorMessage9_1": {},
    "ErrorMessage9_2": {},
    "Form1_1": {},
    "Form1_2": {},
    "homePage": {},
    "Host": {},
    "Icon1": {},
    "Image1": {},
    "Image1_1": {},
    "Image2": {},
    "Image2_1": {},
    "Image3": {},
    "Image3_1": {},
    "Image3_2": {},
    "Image4": {},
    "Image4_1": {},
    "Image4_2": {},
    "Image5": {},
    "Image5_1": {},
    "Image5_2": {},
    "Image5_3": {},
    "Image5_4": {},
    "Image5_5": {},
    "Image5_6": {},
    "Image5_7": {},
    "Label1": {},
    "Label1_1": {},
    "Label1_2": {},
    "Label1_3": {},
    "Label2": {},
    "Label2_1": {},
    "Label3": {},
    "Label3_1": {},
    "Label4": {},
    "Label4_1": {},
    "Label4_2": {},
    "Label5": {},
    "Label5_1": {},
    "Label5_2": {},
    "Label5_3": {},
    "Label5_4": {},
    "Label5_5": {},
    "Label5_6": {},
    "Label5_7": {},
    "Label6": {},
    "Label8": {},
    "NoVendorFound": {},
    "PR": {},
    "purchaseOrderForm": {},
    "purchaseRequstion": {},
    "Rectangle1": {},
    "Rectangle1_1": {},
    "Rectangle1_2": {},
    "Rectangle1_3": {},
    "Rectangle1_4": {},
    "Rectangle1_5": {},
    "Rectangle1_6": {},
    "Rectangle1_7": {},
    "Rectangle2": {},
    "Reg Cost Disb_DataCard1": {},
    "Region_DataCard1": {},
    "Region_DataCard2_1": {},
    "Region_DataCard2_2": {},
    "Replicate_ConfirmationScreen": {},
    "Replicate_HomeSCreen": {},
    "Replicate_PR": {},
    "Replicate_SplashScreen": {},
    "Replicate_Vendor": {},
    "Service and Bussiness Case_DataCard1": {},
    "Service and Bussiness Case_DataCard3_1": {},
    "Service and Bussiness Case_DataCard3_2": {},
    "Service_Provider_Known_DataCard1_1": {},
    "Service_Provider_Known_DataCard1_2": {},
    "splashScreen": {},
    "Start_Date_DataCard1_1": {},
    "Start_Date_DataCard1_2": {},
    "StarVisible1_1": {},
    "StarVisible1_2": {},
    "StarVisible10_1": {},
    "StarVisible10_2": {},
    "StarVisible11_1": {},
    "StarVisible11_2": {},
    "StarVisible12_1": {},
    "StarVisible12_2": {},
    "StarVisible13_1": {},
    "StarVisible13_2": {},
    "StarVisible2_1": {},
    "StarVisible2_2": {},
    "StarVisible3_1": {},
    "StarVisible3_2": {},
    "StarVisible4": {},
    "StarVisible5_1": {},
    "StarVisible5_2": {},
    "StarVisible6": {},
    "StarVisible7": {},
    "StarVisible8": {},
    "StarVisible9_1": {},
    "StarVisible9_2": {},
    "Summary_DataCard1": {},
    "Summary_DataCard2_1": {},
    "Summary_DataCard2_2": {},
    "TextInput1": {},
    "TextInput1_1": {},
    "TextInput1_2": {},
    "TextInput1_3": {},
    "TextInput2": {},
    "TextInput2_1": {},
    "TextInput2_2": {},
    "TextInput2_3": {},
    "TextInput2_4": {},
    "TextInput2_5": {},
    "Unit Cost Disb_DataCard1": {},
    "UnitEntity_DataCard1": {},
    "UnitEntity_DataCard2_1": {},
    "UnitEntity_DataCard2_2": {},
    "Units Needed_DataCard1": {},
    "Units Needed_DataCard2_1": {},
    "Units Needed_DataCard2_2": {},
    "Vendor": {},
    "Vendor_DataCard2_1": {},
    "Vendor_DataCard2_2": {}
  },
  "PCFDynamicSchemaForIRRetrievalEntry": {},
  "PCFTemplateEntry": {},
  "PublishOrderIndices": {
    "App": 0,
    "Button1": 82,
    "Button3": 27,
    "ConfirmationScreen": 3,
    "DataCardKey1_1": 66,
    "DataCardKey1_2": 162,
    "DataCardKey10_1": 48,
    "DataCardKey10_2": 144,
    "DataCardKey11_1": 52,
    "DataCardKey11_2": 148,
    "DataCardKey12_1": 56,
    "DataCardKey12_2": 152,
    "DataCardKey14_1": 60,
    "DataCardKey14_2": 156,
    "DataCardKey15_1": 63,
    "DataCardKey15_2": 159,
    "DataCardKey2_1": 70,
    "DataCardKey2_2": 166,
    "DataCardKey3_1": 74,
    "DataCardKey3_2": 170,
    "DataCardKey4": 92,
    "DataCardKey5_1": 78,
    "DataCardKey5_2": 174,
    "DataCardKey6": 96,
    "DataCardKey7": 100,
    "DataCardKey8": 104,
    "DataCardKey9_1": 44,
    "DataCardKey9_2": 140,
    "DataCardValue1_1": 67,
    "DataCardValue1_2": 163,
    "DataCardValue10_1": 49,
    "DataCardValue10_2": 145,
    "DataCardValue11_1": 53,
    "DataCardValue11_2": 149,
    "DataCardValue12_1": 57,
    "DataCardValue12_2": 153,
    "DataCardValue14_1": 61,
    "DataCardValue14_2": 157,
    "DataCardValue15_1": 64,
    "DataCardValue15_2": 160,
    "DataCardValue2_1": 71,
    "DataCardValue2_2": 167,
    "DataCardValue3_1": 75,
    "DataCardValue3_2": 171,
    "DataCardValue4": 93,
    "DataCardValue5_1": 79,
    "DataCardValue5_2": 175,
    "DataCardValue6": 97,
    "DataCardValue7": 101,
    "DataCardValue8": 105,
    "DataCardValue9_1": 45,
    "DataCardValue9_2": 141,
    "Department_DataCard1": 84,
    "Department_DataCard2_1": 33,
    "Department_DataCard2_2": 129,
    "End_Date_DataCard1_1": 40,
    "End_Date_DataCard1_2": 136,
    "ErrorMessage1_1": 68,
    "ErrorMessage1_2": 164,
    "ErrorMessage10_1": 50,
    "ErrorMessage10_2": 146,
    "ErrorMessage11_1": 54,
    "ErrorMessage11_2": 150,
    "ErrorMessage12_1": 58,
    "ErrorMessage12_2": 154,
    "ErrorMessage13_1": 62,
    "ErrorMessage13_2": 158,
    "ErrorMessage2_1": 72,
    "ErrorMessage2_2": 168,
    "ErrorMessage3_1": 76,
    "ErrorMessage3_2": 172,
    "ErrorMessage4": 94,
    "ErrorMessage5_1": 80,
    "ErrorMessage5_2": 176,
    "ErrorMessage6": 98,
    "ErrorMessage7": 102,
    "ErrorMessage8": 106,
    "ErrorMessage9_1": 46,
    "ErrorMessage9_2": 142,
    "Form1_1": 32,
    "Form1_2": 128,
    "homePage": 8,
    "Host": 0,
    "Icon1": 195,
    "Image1": 186,
    "Image1_1": 178,
    "Image2": 9,
    "Image2_1": 114,
    "Image3": 4,
    "Image3_1": 109,
    "Image3_2": 28,
    "Image4": 5,
    "Image4_1": 110,
    "Image4_2": 29,
    "Image5": 11,
    "Image5_1": 18,
    "Image5_2": 13,
    "Image5_3": 19,
    "Image5_4": 118,
    "Image5_5": 124,
    "Image5_6": 123,
    "Image5_7": 116,
    "Label1": 190,
    "Label1_1": 193,
    "Label1_2": 181,
    "Label1_3": 183,
    "Label2": 188,
    "Label2_1": 179,
    "Label3": 6,
    "Label3_1": 111,
    "Label4": 7,
    "Label4_1": 112,
    "Label4_2": 30,
    "Label5": 21,
    "Label5_1": 20,
    "Label5_2": 15,
    "Label5_3": 14,
    "Label5_4": 125,
    "Label5_5": 120,
    "Label5_6": 119,
    "Label5_7": 126,
    "Label6": 187,
    "Label8": 196,
    "NoVendorFound": 25,
    "PR": 31,
    "purchaseOrderForm": 83,
    "purchaseRequstion": 81,
    "Rectangle1": 10,
    "Rectangle1_1": 16,
    "Rectangle1_2": 12,
    "Rectangle1_3": 17,
    "Rectangle1_4": 115,
    "Rectangle1_5": 121,
    "Rectangle1_6": 117,
    "Rectangle1_7": 122,
    "Rectangle2": 192,
    "Reg Cost Disb_DataCard1": 86,
    "Region_DataCard1": 85,
    "Region_DataCard2_1": 34,
    "Region_DataCard2_2": 130,
    "Replicate_ConfirmationScreen": 108,
    "Replicate_HomeSCreen": 113,
    "Replicate_PR": 127,
    "Replicate_SplashScreen": 177,
    "Replicate_Vendor": 180,
    "Service and Bussiness Case_DataCard1": 90,
    "Service and Bussiness Case_DataCard3_1": 37,
    "Service and Bussiness Case_DataCard3_2": 133,
    "Service_Provider_Known_DataCard1_1": 41,
    "Service_Provider_Known_DataCard1_2": 137,
    "splashScreen": 185,
    "Start_Date_DataCard1_1": 39,
    "Start_Date_DataCard1_2": 135,
    "StarVisible1_1": 65,
    "StarVisible1_2": 161,
    "StarVisible10_1": 47,
    "StarVisible10_2": 143,
    "StarVisible11_1": 51,
    "StarVisible11_2": 147,
    "StarVisible12_1": 55,
    "StarVisible12_2": 151,
    "StarVisible13_1": 59,
    "StarVisible13_2": 155,
    "StarVisible2_1": 69,
    "StarVisible2_2": 165,
    "StarVisible3_1": 73,
    "StarVisible3_2": 169,
    "StarVisible4": 95,
    "StarVisible5_1": 77,
    "StarVisible5_2": 173,
    "StarVisible6": 99,
    "StarVisible7": 103,
    "StarVisible8": 107,
    "StarVisible9_1": 43,
    "StarVisible9_2": 139,
    "Summary_DataCard1": 89,
    "Summary_DataCard2_1": 36,
    "Summary_DataCard2_2": 132,
    "TextInput1": 191,
    "TextInput1_1": 194,
    "TextInput1_2": 182,
    "TextInput1_3": 184,
    "TextInput2": 197,
    "TextInput2_1": 198,
    "TextInput2_2": 199,
    "TextInput2_3": 200,
    "TextInput2_4": 201,
    "TextInput2_5": 202,
    "Unit Cost Disb_DataCard1": 88,
    "UnitEntity_DataCard1": 87,
    "UnitEntity_DataCard2_1": 35,
    "UnitEntity_DataCard2_2": 131,
    "Units Needed_DataCard1": 91,
    "Units Needed_DataCard2_1": 38,
    "Units Needed_DataCard2_2": 134,
    "Vendor": 189,
    "Vendor_DataCard2_1": 42,
    "Vendor_DataCard2_2": 138
  },
  "ResourcesJsonIndices": {
    "Image-Confirmed-cuate": 1,
    "Image-icons8-business-report-100": 2,
    "Image-icons8-login-64": 3,
    "Image-icons8-order-100": 4,
    "Image-icons8-purchase-order-50": 5,
    "Image-icons8-purchase-order-50_1": 6,
    "Image-icons8-user-100": 7,
    "Image-icons8-user-64": 8,
    "Image-icons8-vendor-100": 9,
    "Image-image": 10,
    "Image-image_1": 11,
    "Image-Questions-pana-removebg-preview": 12,
    "Image-Questions-pana-removebg-preview_1": 13,
    "Image-SampleImage": 0,
    "Image-XEBIA2": 14,
    "Image-XebiaBg": 15
  },
  "RuleScreenIdWithoutScreen": {},
  "TemplateVersions": {},
  "VolatileProperties": {
    "AnalysisLoadTime": 0.8861732,
    "ControlCount": {
      "button": 3,
      "datepicker": 4,
      "dropdown": 8,
      "form": 3,
      "icon": 1,
      "image": 19,
      "label": 92,
      "rectangle": 9,
      "richTextEditor": 2,
      "screen": 13,
      "text": 16,
      "toggleSwitch": 2,
      "typedDataCard": 28
    },
    "DeserializationLoadTime": 2.5909637
  },
  "WasLocalDatabaseReferencesEmpty": true
}