{
  "ComponentIndexes": {},
  "ControlUniqueGuids": {},
  "ControlUniqueIds": {
    "addEntity": 70,
    "Amount_DataCard1": 425,
    "Amount_DataCard2": 225,
    "Amount_DataCard2_1": 553,
    "App": 1,
    "approval": 248,
    "Body1": 359,
    "Button1": 465,
    "Button1_1": 301,
    "Button2_2": 26,
    "Button2_3": 25,
    "Button3": 152,
    "Button3_1": 43,
    "Button3_10": 246,
    "Button3_2": 105,
    "Button3_3": 49,
    "Button3_4": 307,
    "Button3_5": 313,
    "Button3_6": 245,
    "Button3_9": 153,
    "CalculatedBudget_DataCard2": 440,
    "CalculatedBudget_DataCard3": 230,
    "CalculatedBudget_DataCard3_1": 558,
    "Created By_DataCard1": 235,
    "Created By_DataCard1_1": 563,
    "Created_DataCard1": 240,
    "Created_DataCard1_1": 568,
    "Currency_DataCard2": 210,
    "Currency_DataCard2_1": 538,
    "Currency_DataCard3": 420,
    "CurrencyRate_DataCard2": 220,
    "CurrencyRate_DataCard2_1": 548,
    "CurrencyRate_DataCard3": 430,
    "DataCardKey1_3": 283,
    "DataCardKey10": 377,
    "DataCardKey10_3": 260,
    "DataCardKey11": 382,
    "DataCardKey11_3": 265,
    "DataCardKey12": 412,
    "DataCardKey12_3": 270,
    "DataCardKey13": 387,
    "DataCardKey14": 35,
    "DataCardKey14_3": 275,
    "DataCardKey15": 40,
    "DataCardKey15_3": 279,
    "DataCardKey16": 442,
    "DataCardKey16_2": 179,
    "DataCardKey16_3": 507,
    "DataCardKey17": 447,
    "DataCardKey18_2": 217,
    "DataCardKey18_3": 545,
    "DataCardKey19": 237,
    "DataCardKey19_1": 565,
    "DataCardKey19_2": 192,
    "DataCardKey19_3": 520,
    "DataCardKey2": 188,
    "DataCardKey2_2": 169,
    "DataCardKey2_3": 497,
    "DataCardKey20": 212,
    "DataCardKey20_1": 540,
    "DataCardKey20_2": 197,
    "DataCardKey20_3": 525,
    "DataCardKey21": 222,
    "DataCardKey21_1": 550,
    "DataCardKey22": 165,
    "DataCardKey22_1": 493,
    "DataCardKey22_2": 207,
    "DataCardKey22_3": 535,
    "DataCardKey23": 15,
    "DataCardKey24": 20,
    "DataCardKey25": 202,
    "DataCardKey25_1": 530,
    "DataCardKey26": 232,
    "DataCardKey26_1": 560,
    "DataCardKey27": 457,
    "DataCardKey28": 184,
    "DataCardKey28_1": 512,
    "DataCardKey29": 227,
    "DataCardKey29_1": 555,
    "DataCardKey3": 407,
    "DataCardKey3_1": 288,
    "DataCardKey3_3": 293,
    "DataCardKey30": 241,
    "DataCardKey30_1": 569,
    "DataCardKey31": 422,
    "DataCardKey32": 432,
    "DataCardKey33": 452,
    "DataCardKey34": 462,
    "DataCardKey36": 516,
    "DataCardKey4": 427,
    "DataCardKey4_2": 174,
    "DataCardKey4_3": 502,
    "DataCardKey44": 117,
    "DataCardKey45": 122,
    "DataCardKey46": 127,
    "DataCardKey47": 132,
    "DataCardKey48": 137,
    "DataCardKey49": 142,
    "DataCardKey5": 397,
    "DataCardKey5_3": 298,
    "DataCardKey50": 147,
    "DataCardKey54": 82,
    "DataCardKey55": 87,
    "DataCardKey56": 92,
    "DataCardKey57": 97,
    "DataCardKey58": 102,
    "DataCardKey6": 392,
    "DataCardKey62": 77,
    "DataCardKey7": 437,
    "DataCardKey8": 402,
    "DataCardKey9": 417,
    "DataCardKey9_3": 255,
    "DataCardValue1_3": 284,
    "DataCardValue10": 378,
    "DataCardValue10_3": 261,
    "DataCardValue11": 383,
    "DataCardValue11_3": 266,
    "DataCardValue12": 413,
    "DataCardValue12_3": 271,
    "DataCardValue13": 388,
    "DataCardValue14": 36,
    "DataCardValue14_3": 276,
    "DataCardValue15": 41,
    "DataCardValue15_3": 280,
    "DataCardValue16": 443,
    "DataCardValue16_2": 180,
    "DataCardValue16_3": 508,
    "DataCardValue17": 448,
    "DataCardValue18_2": 218,
    "DataCardValue18_3": 546,
    "DataCardValue19": 238,
    "DataCardValue19_1": 566,
    "DataCardValue19_2": 193,
    "DataCardValue19_3": 521,
    "DataCardValue2": 189,
    "DataCardValue2_2": 170,
    "DataCardValue2_3": 498,
    "DataCardValue20": 213,
    "DataCardValue20_1": 541,
    "DataCardValue20_2": 198,
    "DataCardValue20_3": 526,
    "DataCardValue21": 223,
    "DataCardValue21_1": 551,
    "DataCardValue22": 166,
    "DataCardValue22_1": 494,
    "DataCardValue22_2": 208,
    "DataCardValue22_3": 536,
    "DataCardValue23": 16,
    "DataCardValue24": 21,
    "DataCardValue25": 203,
    "DataCardValue25_1": 531,
    "DataCardValue26": 233,
    "DataCardValue26_1": 561,
    "DataCardValue27": 458,
    "DataCardValue28": 185,
    "DataCardValue28_1": 513,
    "DataCardValue29": 228,
    "DataCardValue29_1": 556,
    "DataCardValue3": 408,
    "DataCardValue3_1": 289,
    "DataCardValue3_3": 294,
    "DataCardValue30": 242,
    "DataCardValue30_1": 570,
    "DataCardValue31": 423,
    "DataCardValue32": 433,
    "DataCardValue33": 453,
    "DataCardValue34": 463,
    "DataCardValue36": 517,
    "DataCardValue4": 428,
    "DataCardValue4_2": 175,
    "DataCardValue4_3": 503,
    "DataCardValue44": 118,
    "DataCardValue45": 123,
    "DataCardValue46": 128,
    "DataCardValue47": 133,
    "DataCardValue48": 138,
    "DataCardValue49": 143,
    "DataCardValue5": 398,
    "DataCardValue5_3": 299,
    "DataCardValue50": 148,
    "DataCardValue54": 83,
    "DataCardValue55": 88,
    "DataCardValue56": 93,
    "DataCardValue57": 98,
    "DataCardValue58": 103,
    "DataCardValue6": 393,
    "DataCardValue62": 78,
    "DataCardValue7": 438,
    "DataCardValue8": 403,
    "DataCardValue9": 418,
    "DataCardValue9_3": 256,
    "Department_DataCard1_2": 167,
    "Department_DataCard1_3": 495,
    "Department_DataCard2": 375,
    "Department_DataCard2_3": 253,
    "End_Date_DataCard1_1": 286,
    "EndDate_DataCard1": 405,
    "EndDate_DataCard2_2": 195,
    "EndDate_DataCard2_3": 523,
    "entityConfirmation": 308,
    "entityForm": 74,
    "entityListView": 314,
    "ErrorMessage1_3": 285,
    "ErrorMessage10": 379,
    "ErrorMessage10_3": 262,
    "ErrorMessage11": 384,
    "ErrorMessage11_3": 267,
    "ErrorMessage12": 414,
    "ErrorMessage12_3": 272,
    "ErrorMessage13": 389,
    "ErrorMessage13_3": 277,
    "ErrorMessage14": 37,
    "ErrorMessage15": 42,
    "ErrorMessage16": 444,
    "ErrorMessage16_2": 181,
    "ErrorMessage16_3": 509,
    "ErrorMessage17": 449,
    "ErrorMessage18": 239,
    "ErrorMessage18_1": 567,
    "ErrorMessage18_2": 219,
    "ErrorMessage18_3": 547,
    "ErrorMessage19": 214,
    "ErrorMessage19_1": 542,
    "ErrorMessage19_2": 194,
    "ErrorMessage19_3": 522,
    "ErrorMessage2_2": 171,
    "ErrorMessage2_3": 499,
    "ErrorMessage20": 224,
    "ErrorMessage20_1": 552,
    "ErrorMessage20_2": 199,
    "ErrorMessage20_3": 527,
    "ErrorMessage21": 204,
    "ErrorMessage21_1": 532,
    "ErrorMessage22": 234,
    "ErrorMessage22_1": 562,
    "ErrorMessage22_2": 209,
    "ErrorMessage22_3": 537,
    "ErrorMessage23": 17,
    "ErrorMessage24": 22,
    "ErrorMessage25": 459,
    "ErrorMessage26": 186,
    "ErrorMessage26_1": 514,
    "ErrorMessage27": 229,
    "ErrorMessage27_1": 557,
    "ErrorMessage28": 424,
    "ErrorMessage29": 434,
    "ErrorMessage3": 409,
    "ErrorMessage3_1": 290,
    "ErrorMessage3_3": 295,
    "ErrorMessage30": 454,
    "ErrorMessage31": 464,
    "ErrorMessage4": 429,
    "ErrorMessage4_2": 176,
    "ErrorMessage4_3": 504,
    "ErrorMessage41": 119,
    "ErrorMessage42": 124,
    "ErrorMessage43": 129,
    "ErrorMessage44": 134,
    "ErrorMessage45": 139,
    "ErrorMessage46": 144,
    "ErrorMessage47": 149,
    "ErrorMessage5": 399,
    "ErrorMessage5_3": 300,
    "ErrorMessage51": 84,
    "ErrorMessage52": 89,
    "ErrorMessage53": 94,
    "ErrorMessage54": 99,
    "ErrorMessage55": 104,
    "ErrorMessage59": 79,
    "ErrorMessage6": 394,
    "ErrorMessage7": 439,
    "ErrorMessage8": 404,
    "ErrorMessage9": 419,
    "ErrorMessage9_3": 257,
    "Form1_3": 12,
    "Form1_4": 114,
    "Gallery1": 62,
    "Gallery1_1": 321,
    "Gallery1_2": 354,
    "Gallery2": 473,
    "galleryTemplate1": 63,
    "galleryTemplate1_1": 322,
    "galleryTemplate1_2": 355,
    "galleryTemplate2": 474,
    "GroupEntity": 154,
    "GroupVendor": 27,
    "GST#_DataCard2": 135,
    "GST#_DataCard3": 90,
    "homePage": 328,
    "Host": 3,
    "Icon1": 31,
    "Icon1_1": 160,
    "Icon1_10": 319,
    "Icon1_11": 318,
    "Icon1_12": 111,
    "Icon1_13": 353,
    "Icon1_14": 352,
    "Icon1_15": 472,
    "Icon1_16": 471,
    "Icon1_19": 470,
    "Icon1_2": 373,
    "Icon1_20": 59,
    "Icon1_21": 351,
    "Icon1_22": 320,
    "Icon1_3": 73,
    "Icon1_4": 9,
    "Icon1_5": 490,
    "Icon1_7": 251,
    "Icon1_8": 61,
    "Icon1_9": 60,
    "Icon2": 161,
    "Icon2_2": 11,
    "Icon2_3": 113,
    "Icon3": 162,
    "Icon3_1": 112,
    "Icon3_2": 10,
    "ID_DataCard1": 164,
    "ID_DataCard1_1": 492,
    "Image1": 51,
    "Image14": 476,
    "Image2": 329,
    "Image3": 303,
    "Image3_10": 107,
    "Image3_11": 309,
    "Image3_12": 348,
    "Image3_13": 487,
    "Image3_14": 467,
    "Image3_4": 45,
    "Image3_6": 156,
    "Image3_7": 5,
    "Image3_8": 56,
    "Image3_9": 315,
    "Image4": 304,
    "Image4_4": 46,
    "Image4_5": 310,
    "Image5": 361,
    "Image5_2": 334,
    "Image5_3": 335,
    "Image5_4": 340,
    "Image5_5": 345,
    "Image5_6": 341,
    "Image6": 66,
    "Image6_1": 324,
    "Label1": 68,
    "Label11": 151,
    "Label11_1": 244,
    "Label12": 475,
    "Label12_1": 477,
    "Label12_10": 362,
    "Label12_11": 365,
    "Label12_12": 366,
    "Label12_13": 364,
    "Label12_14": 367,
    "Label12_15": 368,
    "Label12_2": 478,
    "Label12_3": 481,
    "Label12_4": 482,
    "Label12_5": 480,
    "Label12_6": 483,
    "Label12_7": 484,
    "Label12_8": 358,
    "Label12_9": 360,
    "Label2": 54,
    "Label3": 305,
    "Label3_2": 47,
    "Label3_3": 311,
    "Label4": 306,
    "Label4_4": 48,
    "Label4_5": 312,
    "Label5_1": 24,
    "Label5_2": 336,
    "Label5_3": 337,
    "Label5_4": 342,
    "Label5_5": 346,
    "Label5_6": 343,
    "Label6": 53,
    "Label9": 30,
    "Label9_1": 372,
    "Label9_10": 317,
    "Label9_11": 110,
    "Label9_12": 350,
    "Label9_13": 489,
    "Label9_14": 469,
    "Label9_2": 72,
    "Label9_5": 250,
    "Label9_6": 159,
    "Label9_7": 8,
    "Label9_8": 58,
    "Label9_9": 331,
    "Legal Address_DataCard2": 125,
    "Legal Address_DataCard3": 80,
    "Legal Entity Name_DataCard2": 120,
    "NextArrow1": 363,
    "NextArrow12": 479,
    "NextArrow2": 67,
    "NextArrow2_1": 325,
    "OperationalApprover_DataCard2": 445,
    "OperationalApproverEmail_DataCard2": 450,
    "PAN#_DataCard2": 130,
    "PAN#_DataCard3": 85,
    "poListView": 347,
    "Rectangle1": 357,
    "Rectangle1_2": 332,
    "Rectangle1_4": 333,
    "Rectangle1_5": 338,
    "Rectangle1_6": 344,
    "Rectangle1_7": 339,
    "Rectangle2": 29,
    "Rectangle2_1": 71,
    "Rectangle2_10": 330,
    "Rectangle2_11": 316,
    "Rectangle2_12": 108,
    "Rectangle2_13": 349,
    "Rectangle2_14": 488,
    "Rectangle2_15": 468,
    "Rectangle2_2": 371,
    "Rectangle2_6": 249,
    "Rectangle2_7": 157,
    "Rectangle2_8": 6,
    "Rectangle2_9": 57,
    "Rectangle3": 64,
    "Rectangle3_1": 323,
    "Rectangle4": 109,
    "Rectangle4_1": 158,
    "Rectangle5_1": 7,
    "Rectangle6_1": 23,
    "Rectangle8": 150,
    "Rectangle8_1": 243,
    "regForm": 163,
    "regForm_1": 491,
    "regGroup": 247,
    "Region_DataCard1": 380,
    "Region_DataCard2_2": 172,
    "Region_DataCard2_3": 258,
    "Region_DataCard2_4": 500,
    "RegionalApprover_DataCard2": 455,
    "RegionalApproverEmail_DataCard2": 460,
    "registration": 370,
    "registrationConfirmation": 302,
    "registrationForm": 374,
    "registrationForm_1": 252,
    "registrationListView": 466,
    "RegistrationNo._DataCard1": 18,
    "RegistrationNo._DataCard2": 38,
    "Separator1": 369,
    "Separator12": 485,
    "Separator2": 69,
    "Separator2_1": 327,
    "Service and Bussiness Case_DataCard3_3": 273,
    "Service_Provider_Known_DataCard1_3": 291,
    "ServiceAndBusinessCase_DataCard2": 395,
    "ServiceAndBusinessCase_DataCard3": 187,
    "ServiceAndBusinessCase_DataCard6": 515,
    "ServiceProvider_DataCard1": 410,
    "ServiceProvider_DataCard2": 200,
    "ServiceProvider_DataCard2_1": 528,
    "Signing Authority_DataCard2": 145,
    "Signing Authority_DataCard3": 100,
    "splashScreen": 50,
    "Start_Date_DataCard1_3": 281,
    "StartDate_DataCard1": 400,
    "StartDate_DataCard2_2": 190,
    "StartDate_DataCard2_3": 518,
    "StarVisible1_3": 282,
    "StarVisible10": 376,
    "StarVisible10_3": 259,
    "StarVisible11": 381,
    "StarVisible11_3": 264,
    "StarVisible12": 411,
    "StarVisible12_3": 269,
    "StarVisible13": 386,
    "StarVisible13_3": 274,
    "StarVisible14": 34,
    "StarVisible15": 39,
    "StarVisible16": 441,
    "StarVisible16_2": 178,
    "StarVisible16_3": 506,
    "StarVisible17": 446,
    "StarVisible18": 236,
    "StarVisible18_1": 564,
    "StarVisible18_2": 216,
    "StarVisible18_3": 544,
    "StarVisible19": 211,
    "StarVisible19_1": 539,
    "StarVisible19_2": 191,
    "StarVisible19_3": 519,
    "StarVisible2_2": 168,
    "StarVisible2_3": 496,
    "StarVisible20": 221,
    "StarVisible20_1": 549,
    "StarVisible20_2": 196,
    "StarVisible20_3": 524,
    "StarVisible21": 201,
    "StarVisible21_1": 529,
    "StarVisible22": 231,
    "StarVisible22_1": 559,
    "StarVisible22_2": 206,
    "StarVisible22_3": 534,
    "StarVisible23": 14,
    "StarVisible24": 19,
    "StarVisible25": 456,
    "StarVisible26": 183,
    "StarVisible26_1": 511,
    "StarVisible27": 226,
    "StarVisible27_1": 554,
    "StarVisible28": 421,
    "StarVisible29": 431,
    "StarVisible3": 406,
    "StarVisible3_1": 287,
    "StarVisible3_3": 292,
    "StarVisible30": 451,
    "StarVisible31": 461,
    "StarVisible4": 426,
    "StarVisible4_2": 173,
    "StarVisible4_3": 501,
    "StarVisible41": 116,
    "StarVisible42": 121,
    "StarVisible43": 126,
    "StarVisible44": 131,
    "StarVisible45": 136,
    "StarVisible46": 141,
    "StarVisible47": 146,
    "StarVisible5": 396,
    "StarVisible5_3": 297,
    "StarVisible51": 81,
    "StarVisible52": 86,
    "StarVisible53": 91,
    "StarVisible54": 96,
    "StarVisible55": 101,
    "StarVisible59": 76,
    "StarVisible6": 391,
    "StarVisible7": 436,
    "StarVisible8": 401,
    "StarVisible9": 416,
    "StarVisible9_3": 254,
    "Subtitle1": 356,
    "Summary_DataCard2_3": 268,
    "summaryEntity": 106,
    "summaryPO": 486,
    "summaryRegistration": 155,
    "summaryVendor": 4,
    "Timer1": 52,
    "Title_DataCard12": 75,
    "Title_DataCard2": 33,
    "Title_DataCard3": 390,
    "Title_DataCard4": 13,
    "Title_DataCard5": 182,
    "Title_DataCard5_1": 510,
    "Title_DataCard8": 115,
    "Title2": 65,
    "Title2_1": 326,
    "UnitEntity_DataCard1": 385,
    "UnitEntity_DataCard2_2": 177,
    "UnitEntity_DataCard2_3": 263,
    "UnitEntity_DataCard2_4": 505,
    "UnitNeeded_DataCard1": 435,
    "UnitNeeded_DataCard2_2": 215,
    "UnitNeeded_DataCard2_3": 543,
    "Units Needed_DataCard2_3": 278,
    "VAT#_DataCard2": 140,
    "VAT#_DataCard3": 95,
    "vendor": 28,
    "Vendor_DataCard1": 415,
    "Vendor_DataCard2_2": 205,
    "Vendor_DataCard2_3": 296,
    "Vendor_DataCard2_4": 533,
    "vendorConfirmation": 44,
    "vendorForm": 32,
    "vendorListView": 55
  },
  "FunctionParamsInvariantScripts": {},
  "FunctionParamsInvariantScriptsOnInstances": {},
  "HeaderLastSavedDateTimeUTC": "08/09/2023 12:56:00",
  "IsLegacyComponentAllowGlobalScopeCase": false,
  "LocalConnectionIDReferences": {
    "1c1f3cde-0c54-4ba4-b415-01278490b886": "\"/providers/microsoft.powerapps/apis/shared_sharepointonline/connections/88cf232da52e48f898a190cbb916092b\"",
    "4320845a-f039-4291-8e4c-6e4835b22bed": "\"/providers/microsoft.powerapps/apis/shared_sharepointonline/connections/88cf232da52e48f898a190cbb916092b\"",
    "f312df8c-ce44-4cc2-a340-fab4d3e66cd3": "\"/providers/microsoft.powerapps/apis/shared_sharepointonline/connections/88cf232da52e48f898a190cbb916092b\""
  },
  "LocalDatabaseReferencesAsEmpty": false,
  "LocalResourceFileNames": {
    "83890830": "0001.jpg",
    "Confirmed-cuate": "0002.png",
    "del": "0003.jpg",
    "Group 54": "0004.png",
    "Group 57": "0005.png",
    "Group 58": "0006.png",
    "Group 59": "0007.png",
    "Group 60": "0008.png",
    "icons8-business-entity-64": "0009.png",
    "icons8-business-report-100": "0010.png",
    "icons8-delete-24": "0011.png",
    "icons8-login-64": "0012.png",
    "icons8-order-100": "0013.png",
    "icons8-purchase-order-50": "0014.png",
    "icons8-purchase-order-50_1": "0015.png",
    "icons8-teamwork-64": "0016.png",
    "icons8-user-100": "0018.png",
    "icons8-user-100 (1)": "0017.png",
    "icons8-user-64": "0019.png",
    "icons8-vendor-100": "0020.png",
    "image": "0022.jpg",
    "image (3)": "0021.png",
    "image_1": "0023.jpg",
    "Inbox cleanup-rafiki": "0024.png",
    "Questions-pana-removebg-preview": "0025.png",
    "Questions-pana-removebg-preview_1": "0026.png",
    "XEBIA2": "0027.jpg",
    "XebiaBg": "0028.jpeg"
  },
  "LocalResourceRootPaths": {
    "83890830": "https://docserverpwaprodweu.blob.core.windows.net/53456290-2750-4b3f-8227-6aaca89effed-1/resource/Assets0Images00001.jpg?sv=2018-03-28&sr=b&sig=dv8julkY5XdJAf3st4555a2ktdDA7FYHFJpGZ88py0M%3D&spr=https&se=2023-08-10T13%3A08%3A44Z&sp=r",
    "Confirmed-cuate": "https://docserverpwaprodweu.blob.core.windows.net/53456290-2750-4b3f-8227-6aaca89effed-1/resource/Assets0Images00002.png?sv=2018-03-28&sr=b&sig=SE5fmqoLnDVFNblh1UCvq%2FIhEHxpTAcKSM5WmT1F3ys%3D&spr=https&se=2023-08-10T13%3A08%3A44Z&sp=r",
    "del": "https://docserverpwaprodweu.blob.core.windows.net/53456290-2750-4b3f-8227-6aaca89effed-1/resource/Assets0Images00003.jpg?sv=2018-03-28&sr=b&sig=uXOkNt2lo24D2nbp7qF0%2FzJ1MvKeH5THWRmNKXZ63Js%3D&spr=https&se=2023-08-10T13%3A08%3A44Z&sp=r",
    "Group 54": "https://docserverpwaprodweu.blob.core.windows.net/53456290-2750-4b3f-8227-6aaca89effed-1/resource/Assets0Images00004.png?sv=2018-03-28&sr=b&sig=qT%2F%2BZpk7oLQnsLIQRZrjzC7Eml5%2FKoPtW4NEStbXiiU%3D&spr=https&se=2023-08-10T13%3A08%3A44Z&sp=r",
    "Group 57": "https://docserverpwaprodweu.blob.core.windows.net/53456290-2750-4b3f-8227-6aaca89effed-1/resource/Assets0Images00005.png?sv=2018-03-28&sr=b&sig=9y2PO%2F4m%2Bkhc9cIyQwirZ6UuNNE1BF%2FOnkHWhySI0%2B4%3D&spr=https&se=2023-08-10T13%3A08%3A44Z&sp=r",
    "Group 58": "https://docserverpwaprodweu.blob.core.windows.net/53456290-2750-4b3f-8227-6aaca89effed-1/resource/Assets0Images00006.png?sv=2018-03-28&sr=b&sig=qYJ45df5RTnA4O3IDImdB3Td7csN6xxqei9HsEcOoxI%3D&spr=https&se=2023-08-10T13%3A08%3A44Z&sp=r",
    "Group 59": "https://docserverpwaprodweu.blob.core.windows.net/53456290-2750-4b3f-8227-6aaca89effed-1/resource/Assets0Images00007.png?sv=2018-03-28&sr=b&sig=zoKH8KsprrehlTNCLX4MK5dkMkuNJcdazzK7Lh6DybQ%3D&spr=https&se=2023-08-10T13%3A08%3A44Z&sp=r",
    "Group 60": "https://docserverpwaprodweu.blob.core.windows.net/53456290-2750-4b3f-8227-6aaca89effed-1/resource/Assets0Images00008.png?sv=2018-03-28&sr=b&sig=HRK4ma4yRBtWsZt6ko50hmKd729anZYHTeUxZ6Yryzs%3D&spr=https&se=2023-08-10T13%3A08%3A44Z&sp=r",
    "icons8-business-entity-64": "https://docserverpwaprodweu.blob.core.windows.net/53456290-2750-4b3f-8227-6aaca89effed-1/resource/Assets0Images00009.png?sv=2018-03-28&sr=b&sig=dCxh7s%2BEy6k87sg5XYWcXIwUQgGZ39IjBRcnt9odzDs%3D&spr=https&se=2023-08-10T13%3A08%3A44Z&sp=r",
    "icons8-business-report-100": "https://docserverpwaprodweu.blob.core.windows.net/53456290-2750-4b3f-8227-6aaca89effed-1/resource/Assets0Images00010.png?sv=2018-03-28&sr=b&sig=58ggibBH5pD5hvfDTcdDfuPlBAKjLL%2BaPwxNMEZVGOM%3D&spr=https&se=2023-08-10T13%3A08%3A44Z&sp=r",
    "icons8-delete-24": "https://docserverpwaprodweu.blob.core.windows.net/53456290-2750-4b3f-8227-6aaca89effed-1/resource/Assets0Images00011.png?sv=2018-03-28&sr=b&sig=G5s30OZS3JopfFwHKTNLvg5pr80qVp80LxJZDypcPDw%3D&spr=https&se=2023-08-10T13%3A08%3A44Z&sp=r",
    "icons8-login-64": "https://docserverpwaprodweu.blob.core.windows.net/53456290-2750-4b3f-8227-6aaca89effed-1/resource/Assets0Images00012.png?sv=2018-03-28&sr=b&sig=aR%2BUYlr9q9ATej7iLBoLAxF9Y9GwojZk6u%2FppXSJMnw%3D&spr=https&se=2023-08-10T13%3A08%3A44Z&sp=r",
    "icons8-order-100": "https://docserverpwaprodweu.blob.core.windows.net/53456290-2750-4b3f-8227-6aaca89effed-1/resource/Assets0Images00013.png?sv=2018-03-28&sr=b&sig=hpyWpsEQEDIOWAmTO3vBNk6i0OQwAadtqjXiBZEsyaw%3D&spr=https&se=2023-08-10T13%3A08%3A44Z&sp=r",
    "icons8-purchase-order-50": "https://docserverpwaprodweu.blob.core.windows.net/53456290-2750-4b3f-8227-6aaca89effed-1/resource/Assets0Images00014.png?sv=2018-03-28&sr=b&sig=T8Bgi1fk%2FH%2Bi9GHP19cUWbWaVh58%2F%2F7kjQxu17cdrw0%3D&spr=https&se=2023-08-10T13%3A08%3A44Z&sp=r",
    "icons8-purchase-order-50_1": "https://docserverpwaprodweu.blob.core.windows.net/53456290-2750-4b3f-8227-6aaca89effed-1/resource/Assets0Images00015.png?sv=2018-03-28&sr=b&sig=cOrv5dagGpG9nLM%2FooSzkudCRAfuZTYHp6FtD4FP3Tw%3D&spr=https&se=2023-08-10T13%3A08%3A44Z&sp=r",
    "icons8-teamwork-64": "https://docserverpwaprodweu.blob.core.windows.net/53456290-2750-4b3f-8227-6aaca89effed-1/resource/Assets0Images00016.png?sv=2018-03-28&sr=b&sig=o766oFn9WkSXbUyFlQAUzg%2BfjsxPHF%2Bz0gxUmuyLz2s%3D&spr=https&se=2023-08-10T13%3A08%3A44Z&sp=r",
    "icons8-user-100": "https://docserverpwaprodweu.blob.core.windows.net/53456290-2750-4b3f-8227-6aaca89effed-1/resource/Assets0Images00018.png?sv=2018-03-28&sr=b&sig=hmaMB%2F0M8bkbhqUvJQUjEYSF9D7q2emZVzsYsLLh1I4%3D&spr=https&se=2023-08-10T13%3A08%3A44Z&sp=r",
    "icons8-user-100 (1)": "https://docserverpwaprodweu.blob.core.windows.net/53456290-2750-4b3f-8227-6aaca89effed-1/resource/Assets0Images00017.png?sv=2018-03-28&sr=b&sig=uOKwPWRMV6eUCpFO4b7zynUqC6mNDF7H0c231ea%2FTVg%3D&spr=https&se=2023-08-10T13%3A08%3A44Z&sp=r",
    "icons8-user-64": "https://docserverpwaprodweu.blob.core.windows.net/53456290-2750-4b3f-8227-6aaca89effed-1/resource/Assets0Images00019.png?sv=2018-03-28&sr=b&sig=uSIt5W27lmeBoAYOTgDrHpI8jta76gci1whlfUP1jiA%3D&spr=https&se=2023-08-10T13%3A08%3A44Z&sp=r",
    "icons8-vendor-100": "https://docserverpwaprodweu.blob.core.windows.net/53456290-2750-4b3f-8227-6aaca89effed-1/resource/Assets0Images00020.png?sv=2018-03-28&sr=b&sig=sCwtgxTADzqAJ2a4z2Gj8dlJLbHPbiVKGgnoFzDMfmM%3D&spr=https&se=2023-08-10T13%3A08%3A44Z&sp=r",
    "image": "https://docserverpwaprodweu.blob.core.windows.net/53456290-2750-4b3f-8227-6aaca89effed-1/resource/Assets0Images00022.jpg?sv=2018-03-28&sr=b&sig=I8xtrXDI065CuiinzdcpiOPgwKWdKjPIkxx0b1amUgM%3D&spr=https&se=2023-08-10T13%3A08%3A44Z&sp=r",
    "image (3)": "https://docserverpwaprodweu.blob.core.windows.net/53456290-2750-4b3f-8227-6aaca89effed-1/resource/Assets0Images00021.png?sv=2018-03-28&sr=b&sig=XcloCZB%2FXXPAKGLhd42mxGsq4RvfPTgq7I0Fh%2BsLqlM%3D&spr=https&se=2023-08-10T13%3A08%3A44Z&sp=r",
    "image_1": "https://docserverpwaprodweu.blob.core.windows.net/53456290-2750-4b3f-8227-6aaca89effed-1/resource/Assets0Images00023.jpg?sv=2018-03-28&sr=b&sig=D4zeuuBA3s8Y0Fr%2BqZfOxecuAhd5BZfMkm5zfKSRWBs%3D&spr=https&se=2023-08-10T13%3A08%3A44Z&sp=r",
    "Inbox cleanup-rafiki": "https://docserverpwaprodweu.blob.core.windows.net/53456290-2750-4b3f-8227-6aaca89effed-1/resource/Assets0Images00024.png?sv=2018-03-28&sr=b&sig=qrwaOTM%2FGW64K9w%2FVdyMzz9JxfzAxfGkwQ1MYuXsRlw%3D&spr=https&se=2023-08-10T13%3A08%3A44Z&sp=r",
    "Questions-pana-removebg-preview": "https://docserverpwaprodweu.blob.core.windows.net/53456290-2750-4b3f-8227-6aaca89effed-1/resource/Assets0Images00025.png?sv=2018-03-28&sr=b&sig=AApfSmPPffKW%2FVWkIIBwQvyqfRNQR5ziPCizPLqiuGY%3D&spr=https&se=2023-08-10T13%3A08%3A44Z&sp=r",
    "Questions-pana-removebg-preview_1": "https://docserverpwaprodweu.blob.core.windows.net/53456290-2750-4b3f-8227-6aaca89effed-1/resource/Assets0Images00026.png?sv=2018-03-28&sr=b&sig=kMt5uHSIfZjtlctHZM5pCSPSq%2BxNRlyud%2FAN5Jpeav8%3D&spr=https&se=2023-08-10T13%3A08%3A44Z&sp=r",
    "XEBIA2": "https://docserverpwaprodweu.blob.core.windows.net/53456290-2750-4b3f-8227-6aaca89effed-1/resource/Assets0Images00027.jpg?sv=2018-03-28&sr=b&sig=nL0LQ8YXTLMI3iP%2Bgv7BvhPe7w0AJduDSnUqEbiivpI%3D&spr=https&se=2023-08-10T13%3A08%3A44Z&sp=r",
    "XebiaBg": "https://docserverpwaprodweu.blob.core.windows.net/53456290-2750-4b3f-8227-6aaca89effed-1/resource/Assets0Images00028.jpeg?sv=2018-03-28&sr=b&sig=pKADRAEdgsuv88x%2FKH5DZ3vuXkBhgF30V%2BRCaOlCKO0%3D&spr=https&se=2023-08-10T13%3A08%3A44Z&sp=r"
  },
  "OldLogoFileName": "logo.jpg",
  "OrderComponentMetadata": {},
  "OrderComponentTemplate": {},
  "OrderDataSource": {
    "ComboBoxSample": 0,
    "currencyRate": 1,
    "CustomGallerySample": 2,
    "department": 3,
    "departmentEntityMapping": 4,
    "Documents": 5,
    "DropDownSample": 6,
    "entity": 7,
    "LegendSample": 8,
    "PieChartSample": 9,
    "region": 10,
    "registration_1": 11,
    "vendor_1": 12
  },
  "OrderGroupControls": {
    "GroupEntity": {
      "Button3": 3,
      "Button3_9": 4,
      "Label11": 2,
      "Rectangle4": 0,
      "Rectangle8": 1
    },
    "GroupVendor": {
      "Button2_2": 4,
      "Button2_3": 3,
      "Label5_1": 2,
      "Rectangle5_1": 0,
      "Rectangle6_1": 1
    },
    "regGroup": {
      "Button3_10": 4,
      "Button3_6": 3,
      "Label11_1": 2,
      "Rectangle4_1": 0,
      "Rectangle8_1": 1
    }
  },
  "OrderPcfTemplate": {},
  "OrderTemplate": {},
  "OrderXMLTemplate": {
    "button": 6,
    "combobox": 9,
    "datepicker": 11,
    "dropdown": 13,
    "form": 4,
    "gallery": 8,
    "htmlViewer": 10,
    "icon": 3,
    "image": 0,
    "label": 2,
    "rectangle": 1,
    "richTextEditor": 14,
    "text": 5,
    "timer": 7,
    "toggleSwitch": 12
  },
  "OverridablePropertiesEntry": {
    "addEntity": {},
    "Amount_DataCard1": {},
    "Amount_DataCard2": {},
    "Amount_DataCard2_1": {},
    "App": {},
    "approval": {},
    "Body1": {},
    "Button1": {},
    "Button1_1": {},
    "Button2_2": {},
    "Button2_3": {},
    "Button3": {},
    "Button3_1": {},
    "Button3_10": {},
    "Button3_2": {},
    "Button3_3": {},
    "Button3_4": {},
    "Button3_5": {},
    "Button3_6": {},
    "Button3_9": {},
    "CalculatedBudget_DataCard2": {},
    "CalculatedBudget_DataCard3": {},
    "CalculatedBudget_DataCard3_1": {},
    "Created By_DataCard1": {},
    "Created By_DataCard1_1": {},
    "Created_DataCard1": {},
    "Created_DataCard1_1": {},
    "Currency_DataCard2": {},
    "Currency_DataCard2_1": {},
    "Currency_DataCard3": {},
    "CurrencyRate_DataCard2": {},
    "CurrencyRate_DataCard2_1": {},
    "CurrencyRate_DataCard3": {},
    "DataCardKey1_3": {},
    "DataCardKey10": {},
    "DataCardKey10_3": {},
    "DataCardKey11": {},
    "DataCardKey11_3": {},
    "DataCardKey12": {},
    "DataCardKey12_3": {},
    "DataCardKey13": {},
    "DataCardKey14": {},
    "DataCardKey14_3": {},
    "DataCardKey15": {},
    "DataCardKey15_3": {},
    "DataCardKey16": {},
    "DataCardKey16_2": {},
    "DataCardKey16_3": {},
    "DataCardKey17": {},
    "DataCardKey18_2": {},
    "DataCardKey18_3": {},
    "DataCardKey19": {},
    "DataCardKey19_1": {},
    "DataCardKey19_2": {},
    "DataCardKey19_3": {},
    "DataCardKey2": {},
    "DataCardKey2_2": {},
    "DataCardKey2_3": {},
    "DataCardKey20": {},
    "DataCardKey20_1": {},
    "DataCardKey20_2": {},
    "DataCardKey20_3": {},
    "DataCardKey21": {},
    "DataCardKey21_1": {},
    "DataCardKey22": {},
    "DataCardKey22_1": {},
    "DataCardKey22_2": {},
    "DataCardKey22_3": {},
    "DataCardKey23": {},
    "DataCardKey24": {},
    "DataCardKey25": {},
    "DataCardKey25_1": {},
    "DataCardKey26": {},
    "DataCardKey26_1": {},
    "DataCardKey27": {},
    "DataCardKey28": {},
    "DataCardKey28_1": {},
    "DataCardKey29": {},
    "DataCardKey29_1": {},
    "DataCardKey3": {},
    "DataCardKey3_1": {},
    "DataCardKey3_3": {},
    "DataCardKey30": {},
    "DataCardKey30_1": {},
    "DataCardKey31": {},
    "DataCardKey32": {},
    "DataCardKey33": {},
    "DataCardKey34": {},
    "DataCardKey36": {},
    "DataCardKey4": {},
    "DataCardKey4_2": {},
    "DataCardKey4_3": {},
    "DataCardKey44": {},
    "DataCardKey45": {},
    "DataCardKey46": {},
    "DataCardKey47": {},
    "DataCardKey48": {},
    "DataCardKey49": {},
    "DataCardKey5": {},
    "DataCardKey5_3": {},
    "DataCardKey50": {},
    "DataCardKey54": {},
    "DataCardKey55": {},
    "DataCardKey56": {},
    "DataCardKey57": {},
    "DataCardKey58": {},
    "DataCardKey6": {},
    "DataCardKey62": {},
    "DataCardKey7": {},
    "DataCardKey8": {},
    "DataCardKey9": {},
    "DataCardKey9_3": {},
    "DataCardValue1_3": {},
    "DataCardValue10": {},
    "DataCardValue10_3": {},
    "DataCardValue11": {},
    "DataCardValue11_3": {},
    "DataCardValue12": {},
    "DataCardValue12_3": {},
    "DataCardValue13": {},
    "DataCardValue14": {},
    "DataCardValue14_3": {},
    "DataCardValue15": {},
    "DataCardValue15_3": {},
    "DataCardValue16": {},
    "DataCardValue16_2": {},
    "DataCardValue16_3": {},
    "DataCardValue17": {},
    "DataCardValue18_2": {},
    "DataCardValue18_3": {},
    "DataCardValue19": {},
    "DataCardValue19_1": {},
    "DataCardValue19_2": {},
    "DataCardValue19_3": {},
    "DataCardValue2": {},
    "DataCardValue2_2": {},
    "DataCardValue2_3": {},
    "DataCardValue20": {},
    "DataCardValue20_1": {},
    "DataCardValue20_2": {},
    "DataCardValue20_3": {},
    "DataCardValue21": {},
    "DataCardValue21_1": {},
    "DataCardValue22": {},
    "DataCardValue22_1": {},
    "DataCardValue22_2": {},
    "DataCardValue22_3": {},
    "DataCardValue23": {},
    "DataCardValue24": {},
    "DataCardValue25": {},
    "DataCardValue25_1": {},
    "DataCardValue26": {},
    "DataCardValue26_1": {},
    "DataCardValue27": {},
    "DataCardValue28": {},
    "DataCardValue28_1": {},
    "DataCardValue29": {},
    "DataCardValue29_1": {},
    "DataCardValue3": {},
    "DataCardValue3_1": {},
    "DataCardValue3_3": {},
    "DataCardValue30": {},
    "DataCardValue30_1": {},
    "DataCardValue31": {},
    "DataCardValue32": {},
    "DataCardValue33": {},
    "DataCardValue34": {},
    "DataCardValue36": {},
    "DataCardValue4": {},
    "DataCardValue4_2": {},
    "DataCardValue4_3": {},
    "DataCardValue44": {},
    "DataCardValue45": {},
    "DataCardValue46": {},
    "DataCardValue47": {},
    "DataCardValue48": {},
    "DataCardValue49": {},
    "DataCardValue5": {},
    "DataCardValue5_3": {},
    "DataCardValue50": {},
    "DataCardValue54": {},
    "DataCardValue55": {},
    "DataCardValue56": {},
    "DataCardValue57": {},
    "DataCardValue58": {},
    "DataCardValue6": {},
    "DataCardValue62": {},
    "DataCardValue7": {},
    "DataCardValue8": {},
    "DataCardValue9": {},
    "DataCardValue9_3": {},
    "Department_DataCard1_2": {},
    "Department_DataCard1_3": {},
    "Department_DataCard2": {},
    "Department_DataCard2_3": {},
    "End_Date_DataCard1_1": {},
    "EndDate_DataCard1": {},
    "EndDate_DataCard2_2": {},
    "EndDate_DataCard2_3": {},
    "entityConfirmation": {},
    "entityForm": {},
    "entityListView": {},
    "ErrorMessage1_3": {},
    "ErrorMessage10": {},
    "ErrorMessage10_3": {},
    "ErrorMessage11": {},
    "ErrorMessage11_3": {},
    "ErrorMessage12": {},
    "ErrorMessage12_3": {},
    "ErrorMessage13": {},
    "ErrorMessage13_3": {},
    "ErrorMessage14": {},
    "ErrorMessage15": {},
    "ErrorMessage16": {},
    "ErrorMessage16_2": {},
    "ErrorMessage16_3": {},
    "ErrorMessage17": {},
    "ErrorMessage18": {},
    "ErrorMessage18_1": {},
    "ErrorMessage18_2": {},
    "ErrorMessage18_3": {},
    "ErrorMessage19": {},
    "ErrorMessage19_1": {},
    "ErrorMessage19_2": {},
    "ErrorMessage19_3": {},
    "ErrorMessage2_2": {},
    "ErrorMessage2_3": {},
    "ErrorMessage20": {},
    "ErrorMessage20_1": {},
    "ErrorMessage20_2": {},
    "ErrorMessage20_3": {},
    "ErrorMessage21": {},
    "ErrorMessage21_1": {},
    "ErrorMessage22": {},
    "ErrorMessage22_1": {},
    "ErrorMessage22_2": {},
    "ErrorMessage22_3": {},
    "ErrorMessage23": {},
    "ErrorMessage24": {},
    "ErrorMessage25": {},
    "ErrorMessage26": {},
    "ErrorMessage26_1": {},
    "ErrorMessage27": {},
    "ErrorMessage27_1": {},
    "ErrorMessage28": {},
    "ErrorMessage29": {},
    "ErrorMessage3": {},
    "ErrorMessage3_1": {},
    "ErrorMessage3_3": {},
    "ErrorMessage30": {},
    "ErrorMessage31": {},
    "ErrorMessage4": {},
    "ErrorMessage4_2": {},
    "ErrorMessage4_3": {},
    "ErrorMessage41": {},
    "ErrorMessage42": {},
    "ErrorMessage43": {},
    "ErrorMessage44": {},
    "ErrorMessage45": {},
    "ErrorMessage46": {},
    "ErrorMessage47": {},
    "ErrorMessage5": {},
    "ErrorMessage5_3": {},
    "ErrorMessage51": {},
    "ErrorMessage52": {},
    "ErrorMessage53": {},
    "ErrorMessage54": {},
    "ErrorMessage55": {},
    "ErrorMessage59": {},
    "ErrorMessage6": {},
    "ErrorMessage7": {},
    "ErrorMessage8": {},
    "ErrorMessage9": {},
    "ErrorMessage9_3": {},
    "Form1_3": {},
    "Form1_4": {},
    "Gallery1": {},
    "Gallery1_1": {},
    "Gallery1_2": {},
    "Gallery2": {},
    "galleryTemplate1": {},
    "galleryTemplate1_1": {},
    "galleryTemplate1_2": {},
    "galleryTemplate2": {},
    "GroupEntity": {},
    "GroupVendor": {},
    "GST#_DataCard2": {},
    "GST#_DataCard3": {},
    "homePage": {},
    "Host": {},
    "Icon1": {},
    "Icon1_1": {},
    "Icon1_10": {},
    "Icon1_11": {},
    "Icon1_12": {},
    "Icon1_13": {},
    "Icon1_14": {},
    "Icon1_15": {},
    "Icon1_16": {},
    "Icon1_19": {},
    "Icon1_2": {},
    "Icon1_20": {},
    "Icon1_21": {},
    "Icon1_22": {},
    "Icon1_3": {},
    "Icon1_4": {},
    "Icon1_5": {},
    "Icon1_7": {},
    "Icon1_8": {},
    "Icon1_9": {},
    "Icon2": {},
    "Icon2_2": {},
    "Icon2_3": {},
    "Icon3": {},
    "Icon3_1": {},
    "Icon3_2": {},
    "ID_DataCard1": {},
    "ID_DataCard1_1": {},
    "Image1": {},
    "Image14": {},
    "Image2": {},
    "Image3": {},
    "Image3_10": {},
    "Image3_11": {},
    "Image3_12": {},
    "Image3_13": {},
    "Image3_14": {},
    "Image3_4": {},
    "Image3_6": {},
    "Image3_7": {},
    "Image3_8": {},
    "Image3_9": {},
    "Image4": {},
    "Image4_4": {},
    "Image4_5": {},
    "Image5": {},
    "Image5_2": {},
    "Image5_3": {},
    "Image5_4": {},
    "Image5_5": {},
    "Image5_6": {},
    "Image6": {},
    "Image6_1": {},
    "Label1": {},
    "Label11": {},
    "Label11_1": {},
    "Label12": {},
    "Label12_1": {},
    "Label12_10": {},
    "Label12_11": {},
    "Label12_12": {},
    "Label12_13": {},
    "Label12_14": {},
    "Label12_15": {},
    "Label12_2": {},
    "Label12_3": {},
    "Label12_4": {},
    "Label12_5": {},
    "Label12_6": {},
    "Label12_7": {},
    "Label12_8": {},
    "Label12_9": {},
    "Label2": {},
    "Label3": {},
    "Label3_2": {},
    "Label3_3": {},
    "Label4": {},
    "Label4_4": {},
    "Label4_5": {},
    "Label5_1": {},
    "Label5_2": {},
    "Label5_3": {},
    "Label5_4": {},
    "Label5_5": {},
    "Label5_6": {},
    "Label6": {},
    "Label9": {},
    "Label9_1": {},
    "Label9_10": {},
    "Label9_11": {},
    "Label9_12": {},
    "Label9_13": {},
    "Label9_14": {},
    "Label9_2": {},
    "Label9_5": {},
    "Label9_6": {},
    "Label9_7": {},
    "Label9_8": {},
    "Label9_9": {},
    "Legal Address_DataCard2": {},
    "Legal Address_DataCard3": {},
    "Legal Entity Name_DataCard2": {},
    "NextArrow1": {},
    "NextArrow12": {},
    "NextArrow2": {},
    "NextArrow2_1": {},
    "OperationalApprover_DataCard2": {},
    "OperationalApproverEmail_DataCard2": {},
    "PAN#_DataCard2": {},
    "PAN#_DataCard3": {},
    "poListView": {},
    "Rectangle1": {},
    "Rectangle1_2": {},
    "Rectangle1_4": {},
    "Rectangle1_5": {},
    "Rectangle1_6": {},
    "Rectangle1_7": {},
    "Rectangle2": {},
    "Rectangle2_1": {},
    "Rectangle2_10": {},
    "Rectangle2_11": {},
    "Rectangle2_12": {},
    "Rectangle2_13": {},
    "Rectangle2_14": {},
    "Rectangle2_15": {},
    "Rectangle2_2": {},
    "Rectangle2_6": {},
    "Rectangle2_7": {},
    "Rectangle2_8": {},
    "Rectangle2_9": {},
    "Rectangle3": {},
    "Rectangle3_1": {},
    "Rectangle4": {},
    "Rectangle4_1": {},
    "Rectangle5_1": {},
    "Rectangle6_1": {},
    "Rectangle8": {},
    "Rectangle8_1": {},
    "regForm": {},
    "regForm_1": {},
    "regGroup": {},
    "Region_DataCard1": {},
    "Region_DataCard2_2": {},
    "Region_DataCard2_3": {},
    "Region_DataCard2_4": {},
    "RegionalApprover_DataCard2": {},
    "RegionalApproverEmail_DataCard2": {},
    "registration": {},
    "registrationConfirmation": {},
    "registrationForm": {},
    "registrationForm_1": {},
    "registrationListView": {},
    "RegistrationNo._DataCard1": {},
    "RegistrationNo._DataCard2": {},
    "Separator1": {},
    "Separator12": {},
    "Separator2": {},
    "Separator2_1": {},
    "Service and Bussiness Case_DataCard3_3": {},
    "Service_Provider_Known_DataCard1_3": {},
    "ServiceAndBusinessCase_DataCard2": {},
    "ServiceAndBusinessCase_DataCard3": {},
    "ServiceAndBusinessCase_DataCard6": {},
    "ServiceProvider_DataCard1": {},
    "ServiceProvider_DataCard2": {},
    "ServiceProvider_DataCard2_1": {},
    "Signing Authority_DataCard2": {},
    "Signing Authority_DataCard3": {},
    "splashScreen": {},
    "Start_Date_DataCard1_3": {},
    "StartDate_DataCard1": {},
    "StartDate_DataCard2_2": {},
    "StartDate_DataCard2_3": {},
    "StarVisible1_3": {},
    "StarVisible10": {},
    "StarVisible10_3": {},
    "StarVisible11": {},
    "StarVisible11_3": {},
    "StarVisible12": {},
    "StarVisible12_3": {},
    "StarVisible13": {},
    "StarVisible13_3": {},
    "StarVisible14": {},
    "StarVisible15": {},
    "StarVisible16": {},
    "StarVisible16_2": {},
    "StarVisible16_3": {},
    "StarVisible17": {},
    "StarVisible18": {},
    "StarVisible18_1": {},
    "StarVisible18_2": {},
    "StarVisible18_3": {},
    "StarVisible19": {},
    "StarVisible19_1": {},
    "StarVisible19_2": {},
    "StarVisible19_3": {},
    "StarVisible2_2": {},
    "StarVisible2_3": {},
    "StarVisible20": {},
    "StarVisible20_1": {},
    "StarVisible20_2": {},
    "StarVisible20_3": {},
    "StarVisible21": {},
    "StarVisible21_1": {},
    "StarVisible22": {},
    "StarVisible22_1": {},
    "StarVisible22_2": {},
    "StarVisible22_3": {},
    "StarVisible23": {},
    "StarVisible24": {},
    "StarVisible25": {},
    "StarVisible26": {},
    "StarVisible26_1": {},
    "StarVisible27": {},
    "StarVisible27_1": {},
    "StarVisible28": {},
    "StarVisible29": {},
    "StarVisible3": {},
    "StarVisible3_1": {},
    "StarVisible3_3": {},
    "StarVisible30": {},
    "StarVisible31": {},
    "StarVisible4": {},
    "StarVisible4_2": {},
    "StarVisible4_3": {},
    "StarVisible41": {},
    "StarVisible42": {},
    "StarVisible43": {},
    "StarVisible44": {},
    "StarVisible45": {},
    "StarVisible46": {},
    "StarVisible47": {},
    "StarVisible5": {},
    "StarVisible5_3": {},
    "StarVisible51": {},
    "StarVisible52": {},
    "StarVisible53": {},
    "StarVisible54": {},
    "StarVisible55": {},
    "StarVisible59": {},
    "StarVisible6": {},
    "StarVisible7": {},
    "StarVisible8": {},
    "StarVisible9": {},
    "StarVisible9_3": {},
    "Subtitle1": {},
    "Summary_DataCard2_3": {},
    "summaryEntity": {},
    "summaryPO": {},
    "summaryRegistration": {},
    "summaryVendor": {},
    "Timer1": {},
    "Title_DataCard12": {},
    "Title_DataCard2": {},
    "Title_DataCard3": {},
    "Title_DataCard4": {},
    "Title_DataCard5": {},
    "Title_DataCard5_1": {},
    "Title_DataCard8": {},
    "Title2": {},
    "Title2_1": {},
    "UnitEntity_DataCard1": {},
    "UnitEntity_DataCard2_2": {},
    "UnitEntity_DataCard2_3": {},
    "UnitEntity_DataCard2_4": {},
    "UnitNeeded_DataCard1": {},
    "UnitNeeded_DataCard2_2": {},
    "UnitNeeded_DataCard2_3": {},
    "Units Needed_DataCard2_3": {},
    "VAT#_DataCard2": {},
    "VAT#_DataCard3": {},
    "vendor": {},
    "Vendor_DataCard1": {},
    "Vendor_DataCard2_2": {},
    "Vendor_DataCard2_3": {},
    "Vendor_DataCard2_4": {},
    "vendorConfirmation": {},
    "vendorForm": {},
    "vendorListView": {}
  },
  "PCFDynamicSchemaForIRRetrievalEntry": {},
  "PCFTemplateEntry": {},
  "PublishOrderIndices": {
    "addEntity": 1,
    "Amount_DataCard1": 95,
    "Amount_DataCard2": 206,
    "Amount_DataCard2_1": 532,
    "App": 0,
    "approval": 39,
    "Body1": 455,
    "Button1": 135,
    "Button1_1": 280,
    "Button2_2": 337,
    "Button2_3": 336,
    "Button3": 402,
    "Button3_1": 314,
    "Button3_10": 227,
    "Button3_2": 438,
    "Button3_3": 342,
    "Button3_4": 285,
    "Button3_5": 443,
    "Button3_6": 226,
    "Button3_9": 403,
    "CalculatedBudget_DataCard2": 110,
    "CalculatedBudget_DataCard3": 211,
    "CalculatedBudget_DataCard3_1": 537,
    "Created By_DataCard1": 216,
    "Created By_DataCard1_1": 542,
    "Created_DataCard1": 221,
    "Created_DataCard1_1": 547,
    "Currency_DataCard2": 191,
    "Currency_DataCard2_1": 517,
    "Currency_DataCard3": 90,
    "CurrencyRate_DataCard2": 201,
    "CurrencyRate_DataCard2_1": 527,
    "CurrencyRate_DataCard3": 100,
    "DataCardKey1_3": 262,
    "DataCardKey10": 47,
    "DataCardKey10_3": 239,
    "DataCardKey11": 52,
    "DataCardKey11_3": 244,
    "DataCardKey12": 82,
    "DataCardKey12_3": 249,
    "DataCardKey13": 57,
    "DataCardKey14": 306,
    "DataCardKey14_3": 254,
    "DataCardKey15": 311,
    "DataCardKey15_3": 258,
    "DataCardKey16": 112,
    "DataCardKey16_2": 160,
    "DataCardKey16_3": 486,
    "DataCardKey17": 117,
    "DataCardKey18_2": 198,
    "DataCardKey18_3": 524,
    "DataCardKey19": 218,
    "DataCardKey19_1": 544,
    "DataCardKey19_2": 173,
    "DataCardKey19_3": 499,
    "DataCardKey2": 169,
    "DataCardKey2_2": 150,
    "DataCardKey2_3": 476,
    "DataCardKey20": 193,
    "DataCardKey20_1": 519,
    "DataCardKey20_2": 178,
    "DataCardKey20_3": 504,
    "DataCardKey21": 203,
    "DataCardKey21_1": 529,
    "DataCardKey22": 146,
    "DataCardKey22_1": 472,
    "DataCardKey22_2": 188,
    "DataCardKey22_3": 514,
    "DataCardKey23": 326,
    "DataCardKey24": 331,
    "DataCardKey25": 183,
    "DataCardKey25_1": 509,
    "DataCardKey26": 213,
    "DataCardKey26_1": 539,
    "DataCardKey27": 127,
    "DataCardKey28": 165,
    "DataCardKey28_1": 491,
    "DataCardKey29": 208,
    "DataCardKey29_1": 534,
    "DataCardKey3": 77,
    "DataCardKey3_1": 267,
    "DataCardKey3_3": 272,
    "DataCardKey30": 222,
    "DataCardKey30_1": 548,
    "DataCardKey31": 92,
    "DataCardKey32": 102,
    "DataCardKey33": 122,
    "DataCardKey34": 132,
    "DataCardKey36": 495,
    "DataCardKey4": 97,
    "DataCardKey4_2": 155,
    "DataCardKey4_3": 481,
    "DataCardKey44": 367,
    "DataCardKey45": 372,
    "DataCardKey46": 377,
    "DataCardKey47": 382,
    "DataCardKey48": 387,
    "DataCardKey49": 392,
    "DataCardKey5": 67,
    "DataCardKey5_3": 277,
    "DataCardKey50": 397,
    "DataCardKey54": 415,
    "DataCardKey55": 420,
    "DataCardKey56": 425,
    "DataCardKey57": 430,
    "DataCardKey58": 435,
    "DataCardKey6": 62,
    "DataCardKey62": 410,
    "DataCardKey7": 107,
    "DataCardKey8": 72,
    "DataCardKey9": 87,
    "DataCardKey9_3": 234,
    "DataCardValue1_3": 263,
    "DataCardValue10": 48,
    "DataCardValue10_3": 240,
    "DataCardValue11": 53,
    "DataCardValue11_3": 245,
    "DataCardValue12": 83,
    "DataCardValue12_3": 250,
    "DataCardValue13": 58,
    "DataCardValue14": 307,
    "DataCardValue14_3": 255,
    "DataCardValue15": 312,
    "DataCardValue15_3": 259,
    "DataCardValue16": 113,
    "DataCardValue16_2": 161,
    "DataCardValue16_3": 487,
    "DataCardValue17": 118,
    "DataCardValue18_2": 199,
    "DataCardValue18_3": 525,
    "DataCardValue19": 219,
    "DataCardValue19_1": 545,
    "DataCardValue19_2": 174,
    "DataCardValue19_3": 500,
    "DataCardValue2": 170,
    "DataCardValue2_2": 151,
    "DataCardValue2_3": 477,
    "DataCardValue20": 194,
    "DataCardValue20_1": 520,
    "DataCardValue20_2": 179,
    "DataCardValue20_3": 505,
    "DataCardValue21": 204,
    "DataCardValue21_1": 530,
    "DataCardValue22": 147,
    "DataCardValue22_1": 473,
    "DataCardValue22_2": 189,
    "DataCardValue22_3": 515,
    "DataCardValue23": 327,
    "DataCardValue24": 332,
    "DataCardValue25": 184,
    "DataCardValue25_1": 510,
    "DataCardValue26": 214,
    "DataCardValue26_1": 540,
    "DataCardValue27": 128,
    "DataCardValue28": 166,
    "DataCardValue28_1": 492,
    "DataCardValue29": 209,
    "DataCardValue29_1": 535,
    "DataCardValue3": 78,
    "DataCardValue3_1": 268,
    "DataCardValue3_3": 273,
    "DataCardValue30": 223,
    "DataCardValue30_1": 549,
    "DataCardValue31": 93,
    "DataCardValue32": 103,
    "DataCardValue33": 123,
    "DataCardValue34": 133,
    "DataCardValue36": 496,
    "DataCardValue4": 98,
    "DataCardValue4_2": 156,
    "DataCardValue4_3": 482,
    "DataCardValue44": 368,
    "DataCardValue45": 373,
    "DataCardValue46": 378,
    "DataCardValue47": 383,
    "DataCardValue48": 388,
    "DataCardValue49": 393,
    "DataCardValue5": 68,
    "DataCardValue5_3": 278,
    "DataCardValue50": 398,
    "DataCardValue54": 416,
    "DataCardValue55": 421,
    "DataCardValue56": 426,
    "DataCardValue57": 431,
    "DataCardValue58": 436,
    "DataCardValue6": 63,
    "DataCardValue62": 411,
    "DataCardValue7": 108,
    "DataCardValue8": 73,
    "DataCardValue9": 88,
    "DataCardValue9_3": 235,
    "Department_DataCard1_2": 148,
    "Department_DataCard1_3": 474,
    "Department_DataCard2": 45,
    "Department_DataCard2_3": 232,
    "End_Date_DataCard1_1": 265,
    "EndDate_DataCard1": 75,
    "EndDate_DataCard2_2": 176,
    "EndDate_DataCard2_3": 502,
    "entityConfirmation": 93,
    "entityForm": 407,
    "entityListView": 99,
    "ErrorMessage1_3": 264,
    "ErrorMessage10": 49,
    "ErrorMessage10_3": 241,
    "ErrorMessage11": 54,
    "ErrorMessage11_3": 246,
    "ErrorMessage12": 84,
    "ErrorMessage12_3": 251,
    "ErrorMessage13": 59,
    "ErrorMessage13_3": 256,
    "ErrorMessage14": 308,
    "ErrorMessage15": 313,
    "ErrorMessage16": 114,
    "ErrorMessage16_2": 162,
    "ErrorMessage16_3": 488,
    "ErrorMessage17": 119,
    "ErrorMessage18": 220,
    "ErrorMessage18_1": 546,
    "ErrorMessage18_2": 200,
    "ErrorMessage18_3": 526,
    "ErrorMessage19": 195,
    "ErrorMessage19_1": 521,
    "ErrorMessage19_2": 175,
    "ErrorMessage19_3": 501,
    "ErrorMessage2_2": 152,
    "ErrorMessage2_3": 478,
    "ErrorMessage20": 205,
    "ErrorMessage20_1": 531,
    "ErrorMessage20_2": 180,
    "ErrorMessage20_3": 506,
    "ErrorMessage21": 185,
    "ErrorMessage21_1": 511,
    "ErrorMessage22": 215,
    "ErrorMessage22_1": 541,
    "ErrorMessage22_2": 190,
    "ErrorMessage22_3": 516,
    "ErrorMessage23": 328,
    "ErrorMessage24": 333,
    "ErrorMessage25": 129,
    "ErrorMessage26": 167,
    "ErrorMessage26_1": 493,
    "ErrorMessage27": 210,
    "ErrorMessage27_1": 536,
    "ErrorMessage28": 94,
    "ErrorMessage29": 104,
    "ErrorMessage3": 79,
    "ErrorMessage3_1": 269,
    "ErrorMessage3_3": 274,
    "ErrorMessage30": 124,
    "ErrorMessage31": 134,
    "ErrorMessage4": 99,
    "ErrorMessage4_2": 157,
    "ErrorMessage4_3": 483,
    "ErrorMessage41": 369,
    "ErrorMessage42": 374,
    "ErrorMessage43": 379,
    "ErrorMessage44": 384,
    "ErrorMessage45": 389,
    "ErrorMessage46": 394,
    "ErrorMessage47": 399,
    "ErrorMessage5": 69,
    "ErrorMessage5_3": 279,
    "ErrorMessage51": 417,
    "ErrorMessage52": 422,
    "ErrorMessage53": 427,
    "ErrorMessage54": 432,
    "ErrorMessage55": 437,
    "ErrorMessage59": 412,
    "ErrorMessage6": 64,
    "ErrorMessage7": 109,
    "ErrorMessage8": 74,
    "ErrorMessage9": 89,
    "ErrorMessage9_3": 236,
    "Form1_3": 323,
    "Form1_4": 364,
    "Gallery1": 292,
    "Gallery1_1": 349,
    "Gallery1_2": 450,
    "Gallery2": 28,
    "galleryTemplate1": 293,
    "galleryTemplate1_1": 350,
    "galleryTemplate1_2": 451,
    "galleryTemplate2": 29,
    "GroupEntity": 359,
    "GroupVendor": 318,
    "GST#_DataCard2": 385,
    "GST#_DataCard3": 423,
    "homePage": 113,
    "Host": 0,
    "Icon1": 302,
    "Icon1_1": 141,
    "Icon1_10": 347,
    "Icon1_11": 346,
    "Icon1_12": 361,
    "Icon1_13": 449,
    "Icon1_14": 448,
    "Icon1_15": 27,
    "Icon1_16": 26,
    "Icon1_19": 25,
    "Icon1_2": 43,
    "Icon1_20": 289,
    "Icon1_21": 447,
    "Icon1_22": 348,
    "Icon1_3": 406,
    "Icon1_4": 320,
    "Icon1_5": 469,
    "Icon1_7": 230,
    "Icon1_8": 291,
    "Icon1_9": 290,
    "Icon2": 142,
    "Icon2_2": 322,
    "Icon2_3": 363,
    "Icon3": 143,
    "Icon3_1": 362,
    "Icon3_2": 321,
    "ID_DataCard1": 145,
    "ID_DataCard1_1": 471,
    "Image1": 0,
    "Image14": 31,
    "Image2": 4,
    "Image3": 281,
    "Image3_10": 356,
    "Image3_11": 439,
    "Image3_12": 444,
    "Image3_13": 466,
    "Image3_14": 22,
    "Image3_4": 338,
    "Image3_6": 136,
    "Image3_7": 315,
    "Image3_8": 286,
    "Image3_9": 343,
    "Image4": 282,
    "Image4_4": 339,
    "Image4_5": 440,
    "Image5": 457,
    "Image5_2": 9,
    "Image5_3": 10,
    "Image5_4": 15,
    "Image5_5": 20,
    "Image5_6": 16,
    "Image6": 296,
    "Image6_1": 352,
    "Label1": 298,
    "Label11": 401,
    "Label11_1": 225,
    "Label12": 30,
    "Label12_1": 32,
    "Label12_10": 458,
    "Label12_11": 461,
    "Label12_12": 462,
    "Label12_13": 460,
    "Label12_14": 463,
    "Label12_15": 464,
    "Label12_2": 33,
    "Label12_3": 36,
    "Label12_4": 37,
    "Label12_5": 35,
    "Label12_6": 38,
    "Label12_7": 39,
    "Label12_8": 454,
    "Label12_9": 456,
    "Label2": 3,
    "Label3": 283,
    "Label3_2": 340,
    "Label3_3": 441,
    "Label4": 284,
    "Label4_4": 341,
    "Label4_5": 442,
    "Label5_1": 335,
    "Label5_2": 11,
    "Label5_3": 12,
    "Label5_4": 17,
    "Label5_5": 21,
    "Label5_6": 18,
    "Label6": 2,
    "Label9": 301,
    "Label9_1": 42,
    "Label9_10": 345,
    "Label9_11": 360,
    "Label9_12": 446,
    "Label9_13": 468,
    "Label9_14": 24,
    "Label9_2": 405,
    "Label9_5": 229,
    "Label9_6": 140,
    "Label9_7": 319,
    "Label9_8": 288,
    "Label9_9": 6,
    "Legal Address_DataCard2": 375,
    "Legal Address_DataCard3": 413,
    "Legal Entity Name_DataCard2": 370,
    "NextArrow1": 459,
    "NextArrow12": 34,
    "NextArrow2": 297,
    "NextArrow2_1": 353,
    "OperationalApprover_DataCard2": 115,
    "OperationalApproverEmail_DataCard2": 120,
    "PAN#_DataCard2": 380,
    "PAN#_DataCard3": 418,
    "poListView": 132,
    "Rectangle1": 453,
    "Rectangle1_2": 7,
    "Rectangle1_4": 8,
    "Rectangle1_5": 13,
    "Rectangle1_6": 19,
    "Rectangle1_7": 14,
    "Rectangle2": 300,
    "Rectangle2_1": 404,
    "Rectangle2_10": 5,
    "Rectangle2_11": 344,
    "Rectangle2_12": 357,
    "Rectangle2_13": 445,
    "Rectangle2_14": 467,
    "Rectangle2_15": 23,
    "Rectangle2_2": 41,
    "Rectangle2_6": 228,
    "Rectangle2_7": 137,
    "Rectangle2_8": 316,
    "Rectangle2_9": 287,
    "Rectangle3": 294,
    "Rectangle3_1": 351,
    "Rectangle4": 358,
    "Rectangle4_1": 138,
    "Rectangle5_1": 317,
    "Rectangle6_1": 334,
    "Rectangle8": 400,
    "Rectangle8_1": 224,
    "regForm": 144,
    "regForm_1": 470,
    "regGroup": 139,
    "Region_DataCard1": 50,
    "Region_DataCard2_2": 153,
    "Region_DataCard2_3": 237,
    "Region_DataCard2_4": 479,
    "RegionalApprover_DataCard2": 125,
    "RegionalApproverEmail_DataCard2": 130,
    "registration": 155,
    "registrationConfirmation": 251,
    "registrationForm": 44,
    "registrationForm_1": 231,
    "registrationListView": 257,
    "RegistrationNo._DataCard1": 329,
    "RegistrationNo._DataCard2": 309,
    "Separator1": 465,
    "Separator12": 40,
    "Separator2": 299,
    "Separator2_1": 355,
    "Service and Bussiness Case_DataCard3_3": 252,
    "Service_Provider_Known_DataCard1_3": 270,
    "ServiceAndBusinessCase_DataCard2": 65,
    "ServiceAndBusinessCase_DataCard3": 168,
    "ServiceAndBusinessCase_DataCard6": 494,
    "ServiceProvider_DataCard1": 80,
    "ServiceProvider_DataCard2": 181,
    "ServiceProvider_DataCard2_1": 507,
    "Signing Authority_DataCard2": 395,
    "Signing Authority_DataCard3": 433,
    "splashScreen": 277,
    "Start_Date_DataCard1_3": 260,
    "StartDate_DataCard1": 70,
    "StartDate_DataCard2_2": 171,
    "StartDate_DataCard2_3": 497,
    "StarVisible1_3": 261,
    "StarVisible10": 46,
    "StarVisible10_3": 238,
    "StarVisible11": 51,
    "StarVisible11_3": 243,
    "StarVisible12": 81,
    "StarVisible12_3": 248,
    "StarVisible13": 56,
    "StarVisible13_3": 253,
    "StarVisible14": 305,
    "StarVisible15": 310,
    "StarVisible16": 111,
    "StarVisible16_2": 159,
    "StarVisible16_3": 485,
    "StarVisible17": 116,
    "StarVisible18": 217,
    "StarVisible18_1": 543,
    "StarVisible18_2": 197,
    "StarVisible18_3": 523,
    "StarVisible19": 192,
    "StarVisible19_1": 518,
    "StarVisible19_2": 172,
    "StarVisible19_3": 498,
    "StarVisible2_2": 149,
    "StarVisible2_3": 475,
    "StarVisible20": 202,
    "StarVisible20_1": 528,
    "StarVisible20_2": 177,
    "StarVisible20_3": 503,
    "StarVisible21": 182,
    "StarVisible21_1": 508,
    "StarVisible22": 212,
    "StarVisible22_1": 538,
    "StarVisible22_2": 187,
    "StarVisible22_3": 513,
    "StarVisible23": 325,
    "StarVisible24": 330,
    "StarVisible25": 126,
    "StarVisible26": 164,
    "StarVisible26_1": 490,
    "StarVisible27": 207,
    "StarVisible27_1": 533,
    "StarVisible28": 91,
    "StarVisible29": 101,
    "StarVisible3": 76,
    "StarVisible3_1": 266,
    "StarVisible3_3": 271,
    "StarVisible30": 121,
    "StarVisible31": 131,
    "StarVisible4": 96,
    "StarVisible4_2": 154,
    "StarVisible4_3": 480,
    "StarVisible41": 366,
    "StarVisible42": 371,
    "StarVisible43": 376,
    "StarVisible44": 381,
    "StarVisible45": 386,
    "StarVisible46": 391,
    "StarVisible47": 396,
    "StarVisible5": 66,
    "StarVisible5_3": 276,
    "StarVisible51": 414,
    "StarVisible52": 419,
    "StarVisible53": 424,
    "StarVisible54": 429,
    "StarVisible55": 434,
    "StarVisible59": 409,
    "StarVisible6": 61,
    "StarVisible7": 106,
    "StarVisible8": 71,
    "StarVisible9": 86,
    "StarVisible9_3": 233,
    "Subtitle1": 452,
    "Summary_DataCard2_3": 247,
    "summaryEntity": 282,
    "summaryPO": 331,
    "summaryRegistration": 416,
    "summaryVendor": 504,
    "Timer1": 1,
    "Title_DataCard12": 408,
    "Title_DataCard2": 304,
    "Title_DataCard3": 60,
    "Title_DataCard4": 324,
    "Title_DataCard5": 163,
    "Title_DataCard5_1": 489,
    "Title_DataCard8": 365,
    "Title2": 295,
    "Title2_1": 354,
    "UnitEntity_DataCard1": 55,
    "UnitEntity_DataCard2_2": 158,
    "UnitEntity_DataCard2_3": 242,
    "UnitEntity_DataCard2_4": 484,
    "UnitNeeded_DataCard1": 105,
    "UnitNeeded_DataCard2_2": 196,
    "UnitNeeded_DataCard2_3": 522,
    "Units Needed_DataCard2_3": 257,
    "VAT#_DataCard2": 390,
    "VAT#_DataCard3": 428,
    "vendor": 528,
    "Vendor_DataCard1": 85,
    "Vendor_DataCard2_2": 186,
    "Vendor_DataCard2_3": 275,
    "Vendor_DataCard2_4": 512,
    "vendorConfirmation": 544,
    "vendorForm": 303,
    "vendorListView": 550
  },
  "ResourcesJsonIndices": {
    "Image-83890830": 1,
    "Image-Confirmed-cuate": 2,
    "Image-del": 3,
    "Image-Group 54": 4,
    "Image-Group 57": 5,
    "Image-Group 58": 6,
    "Image-Group 59": 7,
    "Image-Group 60": 8,
    "Image-icons8-business-entity-64": 9,
    "Image-icons8-business-report-100": 10,
    "Image-icons8-delete-24": 11,
    "Image-icons8-login-64": 12,
    "Image-icons8-order-100": 13,
    "Image-icons8-purchase-order-50": 14,
    "Image-icons8-purchase-order-50_1": 15,
    "Image-icons8-teamwork-64": 16,
    "Image-icons8-user-100": 18,
    "Image-icons8-user-100 (1)": 17,
    "Image-icons8-user-64": 19,
    "Image-icons8-vendor-100": 20,
    "Image-image": 22,
    "Image-image (3)": 21,
    "Image-image_1": 23,
    "Image-Inbox cleanup-rafiki": 24,
    "Image-Questions-pana-removebg-preview": 25,
    "Image-Questions-pana-removebg-preview_1": 26,
    "Image-SampleImage": 0,
    "Image-XEBIA2": 27,
    "Image-XebiaBg": 28
  },
  "RuleScreenIdWithoutScreen": {},
  "TemplateVersions": {},
  "VolatileProperties": {
    "AnalysisLoadTime": 3.0299757,
    "ControlCount": {
      "button": 13,
      "combobox": 17,
      "datepicker": 8,
      "dropdown": 4,
      "form": 8,
      "gallery": 4,
      "galleryTemplate": 4,
      "group": 3,
      "htmlViewer": 2,
      "icon": 30,
      "image": 25,
      "label": 278,
      "rectangle": 31,
      "richTextEditor": 2,
      "screen": 17,
      "text": 37,
      "timer": 1,
      "toggleSwitch": 4,
      "typedDataCard": 79
    },
    "DeserializationLoadTime": 6.8856898
  },
  "WasLocalDatabaseReferencesEmpty": true
}